reg_32/blocks/decoder5_32/decoder5_32.v
`timescale 1ns/1ps
module dec5_31(
    input [4:0] din,
    output [31:0] addr
);
/*always @(*) begin
    addr = 32'b0
    addr[din] = 1'b1
end*/

assign addr = (1 << din); // shifts '1' to the left by din positions
endmodule

reg_32/decoder5_32/decoder5_32_tb.v
`timescale 1ns/1ps
module dec5_32_tb();
reg [4:0] din_tb;
wire [31:0] addr_tb;
dec5_31 uut (
    .din(din_tb),
    .addr(addr_tb)
);
initial begin
    $dumpfile("sim.vcd");
    $dumpvars(0, dec5_32_tb);
    $monitor("Time = %t | Din = %b | Addr = %b", $time, din_tb, addr_tb);
    for(integer i = 0; i < 32; i = i + 1) begin
        din_tb = i; #10;
    end
#1;
$finish;
end
endmodule

reg_32/reg_blocks/decoder5_32/sim.vcd
$date
	Mon Mar 30 19:05:12 2026
$end
$version
	Icarus Verilog
$end
$timescale
	1ps
$end
$scope module dec5_32_tb $end
$var wire 32 ! addr_tb [31:0] $end
$var reg 5 " din_tb [4:0] $end
$scope module uut $end
$var wire 5 # din [4:0] $end
$var wire 32 $ addr [31:0] $end
$upscope $end
$scope begin $ivl_for_loop0 $end
$var integer 32 % i [31:0] $end
$upscope $end
$upscope $end
$enddefinitions $end
$comment Show the parameter values. $end
$dumpall
$end
#0
$dumpvars
b0 %
b1 $
b0 #
b0 "
b1 !
$end
#10000
b10 !
b10 $
b1 "
b1 #
b1 %
#20000
b100 !
b100 $
b10 "
b10 #
b10 %
#30000
b1000 !
b1000 $
b11 "
b11 #
b11 %
#40000
b10000 !
b10000 $
b100 "
b100 #
b100 %
#50000
b100000 !
b100000 $
b101 "
b101 #
b101 %
#60000
b1000000 !
b1000000 $
b110 "
b110 #
b110 %
#70000
b10000000 !
b10000000 $
b111 "
b111 #
b111 %
#80000
b100000000 !
b100000000 $
b1000 "
b1000 #
b1000 %
#90000
b1000000000 !
b1000000000 $
b1001 "
b1001 #
b1001 %
#100000
b10000000000 !
b10000000000 $
b1010 "
b1010 #
b1010 %
#110000
b100000000000 !
b100000000000 $
b1011 "
b1011 #
b1011 %
#120000
b1000000000000 !
b1000000000000 $
b1100 "
b1100 #
b1100 %
#130000
b10000000000000 !
b10000000000000 $
b1101 "
b1101 #
b1101 %
#140000
b100000000000000 !
b100000000000000 $
b1110 "
b1110 #
b1110 %
#150000
b1000000000000000 !
b1000000000000000 $
b1111 "
b1111 #
b1111 %
#160000
b10000000000000000 !
b10000000000000000 $
b10000 "
b10000 #
b10000 %
#170000
b100000000000000000 !
b100000000000000000 $
b10001 "
b10001 #
b10001 %
#180000
b1000000000000000000 !
b1000000000000000000 $
b10010 "
b10010 #
b10010 %
#190000
b10000000000000000000 !
b10000000000000000000 $
b10011 "
b10011 #
b10011 %
#200000
b100000000000000000000 !
b100000000000000000000 $
b10100 "
b10100 #
b10100 %
#210000
b1000000000000000000000 !
b1000000000000000000000 $
b10101 "
b10101 #
b10101 %
#220000
b10000000000000000000000 !
b10000000000000000000000 $
b10110 "
b10110 #
b10110 %
#230000
b100000000000000000000000 !
b100000000000000000000000 $
b10111 "
b10111 #
b10111 %
#240000
b1000000000000000000000000 !
b1000000000000000000000000 $
b11000 "
b11000 #
b11000 %
#250000
b10000000000000000000000000 !
b10000000000000000000000000 $
b11001 "
b11001 #
b11001 %
#260000
b100000000000000000000000000 !
b100000000000000000000000000 $
b11010 "
b11010 #
b11010 %
#270000
b1000000000000000000000000000 !
b1000000000000000000000000000 $
b11011 "
b11011 #
b11011 %
#280000
b10000000000000000000000000000 !
b10000000000000000000000000000 $
b11100 "
b11100 #
b11100 %
#290000
b100000000000000000000000000000 !
b100000000000000000000000000000 $
b11101 "
b11101 #
b11101 %
#300000
b1000000000000000000000000000000 !
b1000000000000000000000000000000 $
b11110 "
b11110 #
b11110 %
#310000
b10000000000000000000000000000000 !
b10000000000000000000000000000000 $
b11111 "
b11111 #
b11111 %
#320000
b100000 %
