pc/pc/pc.v
`timescale 1ns/1ps
module pc(
    input clk,
    input rst,
    input [31:0] pc_next,
    output reg [31:0] pc
);
always @(posedge clk or posedge rst) begin
    if(rst)
        pc <= 32'h0000_0000;
    else
        pc <= pc_next;
end
endmodule

pc/pc_blocks/pc_reg/pc_tb.v
`timescale 1ns/1ps

module pc_tb;
reg clk;
reg rst;
reg [31:0] pc_next;
wire [31:0] pc;

    pc dut (
        .clk(clk),
        .rst(rst),
        .pc_next(pc_next),
        .pc(pc)
    );

    always #5 clk = ~clk;

    initial begin
        $dumpfile("sim.vcd");
        $dumpvars(0,pc_tb);
        clk = 0;
        rst = 1;
        pc_next = 32'b0;
        $monitor("Time=%0t pc=%h", $time, pc);
        #12;
        rst = 0;
        pc_next = 32'h0000_0004;
        #10;
        pc_next = 32'h0000_0008;
        #10;
        pc_next = 32'h0000_000C;
        #10;
        pc_next = 32'h0000_0100;
        #10;
        $finish;
    end

endmodule

pc/pc/sim.vcd
$date
	Fri Apr 10 08:55:07 2026
$end
$version
	Icarus Verilog
$end
$timescale
	1ps
$end
$scope module pc_tb $end
$var wire 32 ! pc [31:0] $end
$var reg 1 " clk $end
$var reg 32 # pc_next [31:0] $end
$var reg 1 $ rst $end
$scope module dut $end
$var wire 1 " clk $end
$var wire 32 % pc_next [31:0] $end
$var wire 1 $ rst $end
$var reg 32 & pc [31:0] $end
$upscope $end
$upscope $end
$enddefinitions $end
$comment Show the parameter values. $end
$dumpall
$end
#0
$dumpvars
b0 &
b0 %
1$
b0 #
0"
b0 !
$end
#5000
1"
#10000
0"
#12000
b100 #
b100 %
0$
#15000
b100 !
b100 &
1"
#20000
0"
#22000
b1000 #
b1000 %
#25000
b1000 !
b1000 &
1"
#30000
0"
#32000
b1100 #
b1100 %
#35000
b1100 !
b1100 &
1"
#40000
0"
#42000
b100000000 #
b100000000 %
#45000
b100000000 !
b100000000 &
1"
