pc/pc_blocks/pc_reg/dff.v
`timescale 1ns/1ps
module dff(
    input [31:0] dff_in, 
    input clk, we, rst,
    output reg [31:0] q, 
    output [31:0] qbar
);
always @(posedge clk) begin
    if (rst) begin
        q <= 32'b0;
    end
    else if (we) begin
        q <= dff_in; 
    end

end
    assign qbar = ~q;
endmodule

reg_32/decoder5_32.v
`timescale 1ns/1ps
module dec5_31(
    input [4:0] dec_in,
    output [31:0] addr
);
/*always @(*) begin
    addr = 32'b0
    addr[din] = 1'b1
end*/

assign addr = (1 << dec_in); // shifts '1' to the left by din positions
endmodule

reg_32/blocks/reg_write_logic/regfile_write.sv
`timescale 1ns/1ps
module regfile(
    input logic [31:0] wd,                  //the write_data accepts 32 bit input
    input clk, we, rst,                     //1 bit clk we and rst
    input [4:0] rd,                         //destination register address
    output logic [31:0][31:0]dout           //output retrieves 32 outputs 32 bit wide
);

logic [31:0] dec_out;            //decoder_output

dec5_31 decoder(                //instantiate decoder
    .dec_in(rd),                //decoder takes destination address
    .addr(dec_out)              //destination address converted to 32 bit
);

genvar i;                                               
generate                                                //generate used for making 32 reg array
    for (i = 0; i < 32; i = i + 1) begin: pipo          //loop begins
        dff dff_inst(                                   //instantiate dff or reg
            .clk(clk),                                  //common clk
            .dff_in(wd),                                //write_data connected to every register
            .rst(rst),                                  //common reset 
            .we((i == 0) ? 1'b0 : (dec_out[i] & we)),     //writes data only if i is not 0, we is [1] and decoder's address is matched
            .q(dout[i])                              //common d_out
        );
    end
endgenerate 
endmodule

reg_32/blocks/reg_write_logic/regfile_write_tb.sv
`timescale 1ns/1ps
module regfile_tb();

    // Testbench signals
    logic [31:0] wd;
    logic clk, we, rst;
    logic [4:0] rd;
    logic [31:0][31:0] dout;
    logic [31:0] dout_mon;

    // Read monitor: updates after posedge, matches regfile timing
    always @(posedge clk) begin
        dout_mon <= dout[rd];
    end

    // Instantiate regfile
    regfile UUT(
        .wd(wd),
        .clk(clk),
        .we(we),
        .rst(rst),
        .rd(rd),
        .dout(dout)
    );

    // Clock generation
    initial clk = 0;
    always #5 clk = ~clk;  // 10ns period

    initial begin
        // VCD dump for waveform viewing
        $dumpfile("sim.vcd");
        $dumpvars(0, regfile_tb);

        // Initialize signals
        rst = 1;
        we = 0;
        wd = 0;
        rd = 0;
        #10;

        // Release reset
        rst = 0;

        // Random writes to registers
        for (integer i = 0; i < 10; i = i + 1) begin
            wd = $urandom();
            rd = $urandom_range(1,31);  // skip x0, always 0 in RISC-V
            we = 1'b1;

            @(posedge clk);   // WRITE happens here
            we = 1'b0;        // Disable write after one clock

            @(posedge clk);   // READ happens here
            $display("Cycle %0d | Written %d to x%0d | Read back %d", i, wd, rd, dout[rd]);
        end

        // Optional: final dump of all registers
        $display("\nFinal Register Values:");
        for (integer j = 0; j < 32; j = j + 1) begin
            $display("x%0d = %d", j, dout[j]);
        end

        $finish;
    end
endmodule

reg_32/reg_write_logic/sim.vcd
$date
	Wed Apr  1 22:31:48 2026
$end
$version
	Icarus Verilog
$end
$timescale
	1ps
$end
$scope module regfile_tb $end
$var wire 1024 ! dout [1023:0] $end
$var reg 1 " clk $end
$var reg 32 # dout_mon [31:0] $end
$var reg 5 $ rd [4:0] $end
$var reg 1 % rst $end
$var reg 32 & wd [31:0] $end
$var reg 1 ' we $end
$scope module UUT $end
$var wire 1 " clk $end
$var wire 5 ( rd [4:0] $end
$var wire 1 % rst $end
$var wire 32 ) wd [31:0] $end
$var wire 1 ' we $end
$var wire 1024 * dout [1023:0] $end
$var wire 32 + dec_out [31:0] $end
$scope begin pipo[0] $end
$var parameter 2 , i $end
$scope module dff_inst $end
$var wire 1 " clk $end
$var wire 32 - dff_in [31:0] $end
$var wire 32 . qbar [31:0] $end
$var wire 1 % rst $end
$var wire 1 / we $end
$var reg 32 0 q [31:0] $end
$upscope $end
$upscope $end
$scope begin pipo[1] $end
$var parameter 2 1 i $end
$scope module dff_inst $end
$var wire 1 " clk $end
$var wire 32 2 dff_in [31:0] $end
$var wire 32 3 qbar [31:0] $end
$var wire 1 % rst $end
$var wire 1 4 we $end
$var reg 32 5 q [31:0] $end
$upscope $end
$upscope $end
$scope begin pipo[2] $end
$var parameter 3 6 i $end
$scope module dff_inst $end
$var wire 1 " clk $end
$var wire 32 7 dff_in [31:0] $end
$var wire 32 8 qbar [31:0] $end
$var wire 1 % rst $end
$var wire 1 9 we $end
$var reg 32 : q [31:0] $end
$upscope $end
$upscope $end
$scope begin pipo[3] $end
$var parameter 3 ; i $end
$scope module dff_inst $end
$var wire 1 " clk $end
$var wire 32 < dff_in [31:0] $end
$var wire 32 = qbar [31:0] $end
$var wire 1 % rst $end
$var wire 1 > we $end
$var reg 32 ? q [31:0] $end
$upscope $end
$upscope $end
$scope begin pipo[4] $end
$var parameter 4 @ i $end
$scope module dff_inst $end
$var wire 1 " clk $end
$var wire 32 A dff_in [31:0] $end
$var wire 32 B qbar [31:0] $end
$var wire 1 % rst $end
$var wire 1 C we $end
$var reg 32 D q [31:0] $end
$upscope $end
$upscope $end
$scope begin pipo[5] $end
$var parameter 4 E i $end
$scope module dff_inst $end
$var wire 1 " clk $end
$var wire 32 F dff_in [31:0] $end
$var wire 32 G qbar [31:0] $end
$var wire 1 % rst $end
$var wire 1 H we $end
$var reg 32 I q [31:0] $end
$upscope $end
$upscope $end
$scope begin pipo[6] $end
$var parameter 4 J i $end
$scope module dff_inst $end
$var wire 1 " clk $end
$var wire 32 K dff_in [31:0] $end
$var wire 32 L qbar [31:0] $end
$var wire 1 % rst $end
$var wire 1 M we $end
$var reg 32 N q [31:0] $end
$upscope $end
$upscope $end
$scope begin pipo[7] $end
$var parameter 4 O i $end
$scope module dff_inst $end
$var wire 1 " clk $end
$var wire 32 P dff_in [31:0] $end
$var wire 32 Q qbar [31:0] $end
$var wire 1 % rst $end
$var wire 1 R we $end
$var reg 32 S q [31:0] $end
$upscope $end
$upscope $end
$scope begin pipo[8] $end
$var parameter 5 T i $end
$scope module dff_inst $end
$var wire 1 " clk $end
$var wire 32 U dff_in [31:0] $end
$var wire 32 V qbar [31:0] $end
$var wire 1 % rst $end
$var wire 1 W we $end
$var reg 32 X q [31:0] $end
$upscope $end
$upscope $end
$scope begin pipo[9] $end
$var parameter 5 Y i $end
$scope module dff_inst $end
$var wire 1 " clk $end
$var wire 32 Z dff_in [31:0] $end
$var wire 32 [ qbar [31:0] $end
$var wire 1 % rst $end
$var wire 1 \ we $end
$var reg 32 ] q [31:0] $end
$upscope $end
$upscope $end
$scope begin pipo[10] $end
$var parameter 5 ^ i $end
$scope module dff_inst $end
$var wire 1 " clk $end
$var wire 32 _ dff_in [31:0] $end
$var wire 32 ` qbar [31:0] $end
$var wire 1 % rst $end
$var wire 1 a we $end
$var reg 32 b q [31:0] $end
$upscope $end
$upscope $end
$scope begin pipo[11] $end
$var parameter 5 c i $end
$scope module dff_inst $end
$var wire 1 " clk $end
$var wire 32 d dff_in [31:0] $end
$var wire 32 e qbar [31:0] $end
$var wire 1 % rst $end
$var wire 1 f we $end
$var reg 32 g q [31:0] $end
$upscope $end
$upscope $end
$scope begin pipo[12] $end
$var parameter 5 h i $end
$scope module dff_inst $end
$var wire 1 " clk $end
$var wire 32 i dff_in [31:0] $end
$var wire 32 j qbar [31:0] $end
$var wire 1 % rst $end
$var wire 1 k we $end
$var reg 32 l q [31:0] $end
$upscope $end
$upscope $end
$scope begin pipo[13] $end
$var parameter 5 m i $end
$scope module dff_inst $end
$var wire 1 " clk $end
$var wire 32 n dff_in [31:0] $end
$var wire 32 o qbar [31:0] $end
$var wire 1 % rst $end
$var wire 1 p we $end
$var reg 32 q q [31:0] $end
$upscope $end
$upscope $end
$scope begin pipo[14] $end
$var parameter 5 r i $end
$scope module dff_inst $end
$var wire 1 " clk $end
$var wire 32 s dff_in [31:0] $end
$var wire 32 t qbar [31:0] $end
$var wire 1 % rst $end
$var wire 1 u we $end
$var reg 32 v q [31:0] $end
$upscope $end
$upscope $end
$scope begin pipo[15] $end
$var parameter 5 w i $end
$scope module dff_inst $end
$var wire 1 " clk $end
$var wire 32 x dff_in [31:0] $end
$var wire 32 y qbar [31:0] $end
$var wire 1 % rst $end
$var wire 1 z we $end
$var reg 32 { q [31:0] $end
$upscope $end
$upscope $end
$scope begin pipo[16] $end
$var parameter 6 | i $end
$scope module dff_inst $end
$var wire 1 " clk $end
$var wire 32 } dff_in [31:0] $end
$var wire 32 ~ qbar [31:0] $end
$var wire 1 % rst $end
$var wire 1 !" we $end
$var reg 32 "" q [31:0] $end
$upscope $end
$upscope $end
$scope begin pipo[17] $end
$var parameter 6 #" i $end
$scope module dff_inst $end
$var wire 1 " clk $end
$var wire 32 $" dff_in [31:0] $end
$var wire 32 %" qbar [31:0] $end
$var wire 1 % rst $end
$var wire 1 &" we $end
$var reg 32 '" q [31:0] $end
$upscope $end
$upscope $end
$scope begin pipo[18] $end
$var parameter 6 (" i $end
$scope module dff_inst $end
$var wire 1 " clk $end
$var wire 32 )" dff_in [31:0] $end
$var wire 32 *" qbar [31:0] $end
$var wire 1 % rst $end
$var wire 1 +" we $end
$var reg 32 ," q [31:0] $end
$upscope $end
$upscope $end
$scope begin pipo[19] $end
$var parameter 6 -" i $end
$scope module dff_inst $end
$var wire 1 " clk $end
$var wire 32 ." dff_in [31:0] $end
$var wire 32 /" qbar [31:0] $end
$var wire 1 % rst $end
$var wire 1 0" we $end
$var reg 32 1" q [31:0] $end
$upscope $end
$upscope $end
$scope begin pipo[20] $end
$var parameter 6 2" i $end
$scope module dff_inst $end
$var wire 1 " clk $end
$var wire 32 3" dff_in [31:0] $end
$var wire 32 4" qbar [31:0] $end
$var wire 1 % rst $end
$var wire 1 5" we $end
$var reg 32 6" q [31:0] $end
$upscope $end
$upscope $end
$scope begin pipo[21] $end
$var parameter 6 7" i $end
$scope module dff_inst $end
$var wire 1 " clk $end
$var wire 32 8" dff_in [31:0] $end
$var wire 32 9" qbar [31:0] $end
$var wire 1 % rst $end
$var wire 1 :" we $end
$var reg 32 ;" q [31:0] $end
$upscope $end
$upscope $end
$scope begin pipo[22] $end
$var parameter 6 <" i $end
$scope module dff_inst $end
$var wire 1 " clk $end
$var wire 32 =" dff_in [31:0] $end
$var wire 32 >" qbar [31:0] $end
$var wire 1 % rst $end
$var wire 1 ?" we $end
$var reg 32 @" q [31:0] $end
$upscope $end
$upscope $end
$scope begin pipo[23] $end
$var parameter 6 A" i $end
$scope module dff_inst $end
$var wire 1 " clk $end
$var wire 32 B" dff_in [31:0] $end
$var wire 32 C" qbar [31:0] $end
$var wire 1 % rst $end
$var wire 1 D" we $end
$var reg 32 E" q [31:0] $end
$upscope $end
$upscope $end
$scope begin pipo[24] $end
$var parameter 6 F" i $end
$scope module dff_inst $end
$var wire 1 " clk $end
$var wire 32 G" dff_in [31:0] $end
$var wire 32 H" qbar [31:0] $end
$var wire 1 % rst $end
$var wire 1 I" we $end
$var reg 32 J" q [31:0] $end
$upscope $end
$upscope $end
$scope begin pipo[25] $end
$var parameter 6 K" i $end
$scope module dff_inst $end
$var wire 1 " clk $end
$var wire 32 L" dff_in [31:0] $end
$var wire 32 M" qbar [31:0] $end
$var wire 1 % rst $end
$var wire 1 N" we $end
$var reg 32 O" q [31:0] $end
$upscope $end
$upscope $end
$scope begin pipo[26] $end
$var parameter 6 P" i $end
$scope module dff_inst $end
$var wire 1 " clk $end
$var wire 32 Q" dff_in [31:0] $end
$var wire 32 R" qbar [31:0] $end
$var wire 1 % rst $end
$var wire 1 S" we $end
$var reg 32 T" q [31:0] $end
$upscope $end
$upscope $end
$scope begin pipo[27] $end
$var parameter 6 U" i $end
$scope module dff_inst $end
$var wire 1 " clk $end
$var wire 32 V" dff_in [31:0] $end
$var wire 32 W" qbar [31:0] $end
$var wire 1 % rst $end
$var wire 1 X" we $end
$var reg 32 Y" q [31:0] $end
$upscope $end
$upscope $end
$scope begin pipo[28] $end
$var parameter 6 Z" i $end
$scope module dff_inst $end
$var wire 1 " clk $end
$var wire 32 [" dff_in [31:0] $end
$var wire 32 \" qbar [31:0] $end
$var wire 1 % rst $end
$var wire 1 ]" we $end
$var reg 32 ^" q [31:0] $end
$upscope $end
$upscope $end
$scope begin pipo[29] $end
$var parameter 6 _" i $end
$scope module dff_inst $end
$var wire 1 " clk $end
$var wire 32 `" dff_in [31:0] $end
$var wire 32 a" qbar [31:0] $end
$var wire 1 % rst $end
$var wire 1 b" we $end
$var reg 32 c" q [31:0] $end
$upscope $end
$upscope $end
$scope begin pipo[30] $end
$var parameter 6 d" i $end
$scope module dff_inst $end
$var wire 1 " clk $end
$var wire 32 e" dff_in [31:0] $end
$var wire 32 f" qbar [31:0] $end
$var wire 1 % rst $end
$var wire 1 g" we $end
$var reg 32 h" q [31:0] $end
$upscope $end
$upscope $end
$scope begin pipo[31] $end
$var parameter 6 i" i $end
$scope module dff_inst $end
$var wire 1 " clk $end
$var wire 32 j" dff_in [31:0] $end
$var wire 32 k" qbar [31:0] $end
$var wire 1 % rst $end
$var wire 1 l" we $end
$var reg 32 m" q [31:0] $end
$upscope $end
$upscope $end
$scope module decoder $end
$var wire 5 n" dec_in [4:0] $end
$var wire 32 o" addr [31:0] $end
$upscope $end
$upscope $end
$scope begin $ivl_for_loop0 $end
$var integer 32 p" i [31:0] $end
$upscope $end
$scope begin $ivl_for_loop1 $end
$var integer 32 q" j [31:0] $end
$upscope $end
$upscope $end
$enddefinitions $end
$comment Show the parameter values. $end
$dumpall
b11111 i"
b11110 d"
b11101 _"
b11100 Z"
b11011 U"
b11010 P"
b11001 K"
b11000 F"
b10111 A"
b10110 <"
b10101 7"
b10100 2"
b10011 -"
b10010 ("
b10001 #"
b10000 |
b1111 w
b1110 r
b1101 m
b1100 h
b1011 c
b1010 ^
b1001 Y
b1000 T
b111 O
b110 J
b101 E
b100 @
b11 ;
b10 6
b1 1
b0 ,
$end
#0
$dumpvars
bx q"
bx p"
b1 o"
b0 n"
bx m"
0l"
bx k"
b0 j"
bx h"
0g"
bx f"
b0 e"
bx c"
0b"
bx a"
b0 `"
bx ^"
0]"
bx \"
b0 ["
bx Y"
0X"
bx W"
b0 V"
bx T"
0S"
bx R"
b0 Q"
bx O"
0N"
bx M"
b0 L"
bx J"
0I"
bx H"
b0 G"
bx E"
0D"
bx C"
b0 B"
bx @"
0?"
bx >"
b0 ="
bx ;"
0:"
bx 9"
b0 8"
bx 6"
05"
bx 4"
b0 3"
bx 1"
00"
bx /"
b0 ."
bx ,"
0+"
bx *"
b0 )"
bx '"
0&"
bx %"
b0 $"
bx ""
0!"
bx ~
b0 }
bx {
0z
bx y
b0 x
bx v
0u
bx t
b0 s
bx q
0p
bx o
b0 n
bx l
0k
bx j
b0 i
bx g
0f
bx e
b0 d
bx b
0a
bx `
b0 _
bx ]
0\
bx [
b0 Z
bx X
0W
bx V
b0 U
bx S
0R
bx Q
b0 P
bx N
0M
bx L
b0 K
bx I
0H
bx G
b0 F
bx D
0C
bx B
b0 A
bx ?
0>
bx =
b0 <
bx :
09
bx 8
b0 7
bx 5
04
bx 3
b0 2
bx 0
0/
bx .
b0 -
b1 +
bx *
b0 )
b0 (
0'
b0 &
1%
b0 $
bx #
0"
bx !
$end
#5000
b11111111111111111111111111111111 .
b11111111111111111111111111111111 3
b11111111111111111111111111111111 8
b11111111111111111111111111111111 =
b11111111111111111111111111111111 B
b11111111111111111111111111111111 G
b11111111111111111111111111111111 L
b11111111111111111111111111111111 Q
b11111111111111111111111111111111 V
b11111111111111111111111111111111 [
b11111111111111111111111111111111 `
b11111111111111111111111111111111 e
b11111111111111111111111111111111 j
b11111111111111111111111111111111 o
b11111111111111111111111111111111 t
b11111111111111111111111111111111 y
b11111111111111111111111111111111 ~
b11111111111111111111111111111111 %"
b11111111111111111111111111111111 *"
b11111111111111111111111111111111 /"
b11111111111111111111111111111111 4"
b11111111111111111111111111111111 9"
b11111111111111111111111111111111 >"
b11111111111111111111111111111111 C"
b11111111111111111111111111111111 H"
b11111111111111111111111111111111 M"
b11111111111111111111111111111111 R"
b11111111111111111111111111111111 W"
b11111111111111111111111111111111 \"
b11111111111111111111111111111111 a"
b11111111111111111111111111111111 f"
b11111111111111111111111111111111 k"
b0 0
b0 5
b0 :
b0 ?
b0 D
b0 I
b0 N
b0 S
b0 X
b0 ]
b0 b
b0 g
b0 l
b0 q
b0 v
b0 {
b0 ""
b0 '"
b0 ,"
b0 1"
b0 6"
b0 ;"
b0 @"
b0 E"
b0 J"
b0 O"
b0 T"
b0 Y"
b0 ^"
b0 c"
b0 h"
b0 !
b0 *
b0 m"
1"
#10000
1W
0"
1'
b100000000 +
b100000000 o"
b1000 $
b1000 (
b1000 n"
b10010010000101010011010100100100 &
b10010010000101010011010100100100 )
b10010010000101010011010100100100 -
b10010010000101010011010100100100 2
b10010010000101010011010100100100 7
b10010010000101010011010100100100 <
b10010010000101010011010100100100 A
b10010010000101010011010100100100 F
b10010010000101010011010100100100 K
b10010010000101010011010100100100 P
b10010010000101010011010100100100 U
b10010010000101010011010100100100 Z
b10010010000101010011010100100100 _
b10010010000101010011010100100100 d
b10010010000101010011010100100100 i
b10010010000101010011010100100100 n
b10010010000101010011010100100100 s
b10010010000101010011010100100100 x
b10010010000101010011010100100100 }
b10010010000101010011010100100100 $"
b10010010000101010011010100100100 )"
b10010010000101010011010100100100 ."
b10010010000101010011010100100100 3"
b10010010000101010011010100100100 8"
b10010010000101010011010100100100 ="
b10010010000101010011010100100100 B"
b10010010000101010011010100100100 G"
b10010010000101010011010100100100 L"
b10010010000101010011010100100100 Q"
b10010010000101010011010100100100 V"
b10010010000101010011010100100100 ["
b10010010000101010011010100100100 `"
b10010010000101010011010100100100 e"
b10010010000101010011010100100100 j"
b0 p"
0%
#15000
b1101101111010101100101011011011 V
b0 #
b100100100001010100110101001001000000000000000000000000000000000000000000000000000000000000000000000000000000000000000000000000000000000000000000000000000000000000000000000000000000000000000000000000000000000000000000000000000000000000000000000000000000000000000000000000000000000000000000 !
b100100100001010100110101001001000000000000000000000000000000000000000000000000000000000000000000000000000000000000000000000000000000000000000000000000000000000000000000000000000000000000000000000000000000000000000000000000000000000000000000000000000000000000000000000000000000000000000000 *
b10010010000101010011010100100100 X
0W
0'
1"
#20000
0"
#25000
b10010010000101010011010100100100 #
1R
1'
b10000000 +
b10000000 o"
b111 $
b111 (
b111 n"
b100100001001101011000001001 &
b100100001001101011000001001 )
b100100001001101011000001001 -
b100100001001101011000001001 2
b100100001001101011000001001 7
b100100001001101011000001001 <
b100100001001101011000001001 A
b100100001001101011000001001 F
b100100001001101011000001001 K
b100100001001101011000001001 P
b100100001001101011000001001 U
b100100001001101011000001001 Z
b100100001001101011000001001 _
b100100001001101011000001001 d
b100100001001101011000001001 i
b100100001001101011000001001 n
b100100001001101011000001001 s
b100100001001101011000001001 x
b100100001001101011000001001 }
b100100001001101011000001001 $"
b100100001001101011000001001 )"
b100100001001101011000001001 ."
b100100001001101011000001001 3"
b100100001001101011000001001 8"
b100100001001101011000001001 ="
b100100001001101011000001001 B"
b100100001001101011000001001 G"
b100100001001101011000001001 L"
b100100001001101011000001001 Q"
b100100001001101011000001001 V"
b100100001001101011000001001 ["
b100100001001101011000001001 `"
b100100001001101011000001001 e"
b100100001001101011000001001 j"
b1 p"
1"
#30000
0"
#35000
b11111011011110110010100111110110 Q
b0 #
b100100100001010100110101001001000000010010000100110101100000100100000000000000000000000000000000000000000000000000000000000000000000000000000000000000000000000000000000000000000000000000000000000000000000000000000000000000000000000000000000000000000000000000000000000000000000000000000000 !
b100100100001010100110101001001000000010010000100110101100000100100000000000000000000000000000000000000000000000000000000000000000000000000000000000000000000000000000000000000000000000000000000000000000000000000000000000000000000000000000000000000000000000000000000000000000000000000000000 *
b100100001001101011000001001 S
0R
0'
1"
#40000
0"
#45000
b100100001001101011000001001 #
1N"
1'
b10000000000000000000000000 +
b10000000000000000000000000 o"
b11001 $
b11001 (
b11001 n"
b10000110101110010111101100001101 &
b10000110101110010111101100001101 )
b10000110101110010111101100001101 -
b10000110101110010111101100001101 2
b10000110101110010111101100001101 7
b10000110101110010111101100001101 <
b10000110101110010111101100001101 A
b10000110101110010111101100001101 F
b10000110101110010111101100001101 K
b10000110101110010111101100001101 P
b10000110101110010111101100001101 U
b10000110101110010111101100001101 Z
b10000110101110010111101100001101 _
b10000110101110010111101100001101 d
b10000110101110010111101100001101 i
b10000110101110010111101100001101 n
b10000110101110010111101100001101 s
b10000110101110010111101100001101 x
b10000110101110010111101100001101 }
b10000110101110010111101100001101 $"
b10000110101110010111101100001101 )"
b10000110101110010111101100001101 ."
b10000110101110010111101100001101 3"
b10000110101110010111101100001101 8"
b10000110101110010111101100001101 ="
b10000110101110010111101100001101 B"
b10000110101110010111101100001101 G"
b10000110101110010111101100001101 L"
b10000110101110010111101100001101 Q"
b10000110101110010111101100001101 V"
b10000110101110010111101100001101 ["
b10000110101110010111101100001101 `"
b10000110101110010111101100001101 e"
b10000110101110010111101100001101 j"
b10 p"
1"
#50000
0"
#55000
b1111001010001101000010011110010 M"
b0 #
b1000011010111001011110110000110100000000000000000000000000000000000000000000000000000000000000000000000000000000000000000000000000000000000000000000000000000000000000000000000000000000000000000000000000000000000000000000000000000000000000000000000000000000000000000000000000000000000000000000000000000000000000000000000000000000000000000000000000000000000000000000000000000000000000000000000000000000000000000000000000000000000000000000000000000000000000000000000000000000000000000000000000000000000000000000000000000000000000000000000000000000100100100001010100110101001001000000010010000100110101100000100100000000000000000000000000000000000000000000000000000000000000000000000000000000000000000000000000000000000000000000000000000000000000000000000000000000000000000000000000000000000000000000000000000000000000000000000000000000 !
b1000011010111001011110110000110100000000000000000000000000000000000000000000000000000000000000000000000000000000000000000000000000000000000000000000000000000000000000000000000000000000000000000000000000000000000000000000000000000000000000000000000000000000000000000000000000000000000000000000000000000000000000000000000000000000000000000000000000000000000000000000000000000000000000000000000000000000000000000000000000000000000000000000000000000000000000000000000000000000000000000000000000000000000000000000000000000000000000000000000000000000100100100001010100110101001001000000010010000100110101100000100100000000000000000000000000000000000000000000000000000000000000000000000000000000000000000000000000000000000000000000000000000000000000000000000000000000000000000000000000000000000000000000000000000000000000000000000000000000 *
b10000110101110010111101100001101 O"
0N"
0'
1"
#60000
0"
#65000
b10000110101110010111101100001101 #
19
1'
b100 +
b100 o"
b10 $
b10 (
b10 n"
b110010110000101000010001100101 &
b110010110000101000010001100101 )
b110010110000101000010001100101 -
b110010110000101000010001100101 2
b110010110000101000010001100101 7
b110010110000101000010001100101 <
b110010110000101000010001100101 A
b110010110000101000010001100101 F
b110010110000101000010001100101 K
b110010110000101000010001100101 P
b110010110000101000010001100101 U
b110010110000101000010001100101 Z
b110010110000101000010001100101 _
b110010110000101000010001100101 d
b110010110000101000010001100101 i
b110010110000101000010001100101 n
b110010110000101000010001100101 s
b110010110000101000010001100101 x
b110010110000101000010001100101 }
b110010110000101000010001100101 $"
b110010110000101000010001100101 )"
b110010110000101000010001100101 ."
b110010110000101000010001100101 3"
b110010110000101000010001100101 8"
b110010110000101000010001100101 ="
b110010110000101000010001100101 B"
b110010110000101000010001100101 G"
b110010110000101000010001100101 L"
b110010110000101000010001100101 Q"
b110010110000101000010001100101 V"
b110010110000101000010001100101 ["
b110010110000101000010001100101 `"
b110010110000101000010001100101 e"
b110010110000101000010001100101 j"
b11 p"
1"
#70000
0"
#75000
b11001101001111010111101110011010 8
b0 #
b1000011010111001011110110000110100000000000000000000000000000000000000000000000000000000000000000000000000000000000000000000000000000000000000000000000000000000000000000000000000000000000000000000000000000000000000000000000000000000000000000000000000000000000000000000000000000000000000000000000000000000000000000000000000000000000000000000000000000000000000000000000000000000000000000000000000000000000000000000000000000000000000000000000000000000000000000000000000000000000000000000000000000000000000000000000000000000000000000000000000000000100100100001010100110101001001000000010010000100110101100000100100000000000000000000000000000000000000000000000000000000000000000000000000000000000000000000000000000000000000000000000000000000001100101100001010000100011001010000000000000000000000000000000000000000000000000000000000000000 !
b1000011010111001011110110000110100000000000000000000000000000000000000000000000000000000000000000000000000000000000000000000000000000000000000000000000000000000000000000000000000000000000000000000000000000000000000000000000000000000000000000000000000000000000000000000000000000000000000000000000000000000000000000000000000000000000000000000000000000000000000000000000000000000000000000000000000000000000000000000000000000000000000000000000000000000000000000000000000000000000000000000000000000000000000000000000000000000000000000000000000000000100100100001010100110101001001000000010010000100110101100000100100000000000000000000000000000000000000000000000000000000000000000000000000000000000000000000000000000000000000000000000000000000001100101100001010000100011001010000000000000000000000000000000000000000000000000000000000000000 *
b110010110000101000010001100101 :
09
0'
1"
#80000
0"
#85000
b110010110000101000010001100101 #
1&"
1'
b100000000000000000 +
b100000000000000000 o"
b10001 $
b10001 (
b10001 n"
b10000000111100111110001100000001 &
b10000000111100111110001100000001 )
b10000000111100111110001100000001 -
b10000000111100111110001100000001 2
b10000000111100111110001100000001 7
b10000000111100111110001100000001 <
b10000000111100111110001100000001 A
b10000000111100111110001100000001 F
b10000000111100111110001100000001 K
b10000000111100111110001100000001 P
b10000000111100111110001100000001 U
b10000000111100111110001100000001 Z
b10000000111100111110001100000001 _
b10000000111100111110001100000001 d
b10000000111100111110001100000001 i
b10000000111100111110001100000001 n
b10000000111100111110001100000001 s
b10000000111100111110001100000001 x
b10000000111100111110001100000001 }
b10000000111100111110001100000001 $"
b10000000111100111110001100000001 )"
b10000000111100111110001100000001 ."
b10000000111100111110001100000001 3"
b10000000111100111110001100000001 8"
b10000000111100111110001100000001 ="
b10000000111100111110001100000001 B"
b10000000111100111110001100000001 G"
b10000000111100111110001100000001 L"
b10000000111100111110001100000001 Q"
b10000000111100111110001100000001 V"
b10000000111100111110001100000001 ["
b10000000111100111110001100000001 `"
b10000000111100111110001100000001 e"
b10000000111100111110001100000001 j"
b100 p"
1"
#90000
0"
#95000
b1111111000011000001110011111110 %"
b0 #
b1000011010111001011110110000110100000000000000000000000000000000000000000000000000000000000000000000000000000000000000000000000000000000000000000000000000000000000000000000000000000000000000000000000000000000000000000000000000000000000000000000000000000000100000001111001111100011000000010000000000000000000000000000000000000000000000000000000000000000000000000000000000000000000000000000000000000000000000000000000000000000000000000000000000000000000000000000000000000000000000000000000000000000000000000000000000000000000000000000000000000000100100100001010100110101001001000000010010000100110101100000100100000000000000000000000000000000000000000000000000000000000000000000000000000000000000000000000000000000000000000000000000000000001100101100001010000100011001010000000000000000000000000000000000000000000000000000000000000000 !
b1000011010111001011110110000110100000000000000000000000000000000000000000000000000000000000000000000000000000000000000000000000000000000000000000000000000000000000000000000000000000000000000000000000000000000000000000000000000000000000000000000000000000000100000001111001111100011000000010000000000000000000000000000000000000000000000000000000000000000000000000000000000000000000000000000000000000000000000000000000000000000000000000000000000000000000000000000000000000000000000000000000000000000000000000000000000000000000000000000000000000000100100100001010100110101001001000000010010000100110101100000100100000000000000000000000000000000000000000000000000000000000000000000000000000000000000000000000000000000000000000000000000000000001100101100001010000100011001010000000000000000000000000000000000000000000000000000000000000000 *
b10000000111100111110001100000001 '"
0&"
0'
1"
#100000
0"
#105000
b10000000111100111110001100000001 #
15"
1'
b100000000000000000000 +
b100000000000000000000 o"
b10100 $
b10100 (
b10100 n"
b10111011001000111111000101110110 &
b10111011001000111111000101110110 )
b10111011001000111111000101110110 -
b10111011001000111111000101110110 2
b10111011001000111111000101110110 7
b10111011001000111111000101110110 <
b10111011001000111111000101110110 A
b10111011001000111111000101110110 F
b10111011001000111111000101110110 K
b10111011001000111111000101110110 P
b10111011001000111111000101110110 U
b10111011001000111111000101110110 Z
b10111011001000111111000101110110 _
b10111011001000111111000101110110 d
b10111011001000111111000101110110 i
b10111011001000111111000101110110 n
b10111011001000111111000101110110 s
b10111011001000111111000101110110 x
b10111011001000111111000101110110 }
b10111011001000111111000101110110 $"
b10111011001000111111000101110110 )"
b10111011001000111111000101110110 ."
b10111011001000111111000101110110 3"
b10111011001000111111000101110110 8"
b10111011001000111111000101110110 ="
b10111011001000111111000101110110 B"
b10111011001000111111000101110110 G"
b10111011001000111111000101110110 L"
b10111011001000111111000101110110 Q"
b10111011001000111111000101110110 V"
b10111011001000111111000101110110 ["
b10111011001000111111000101110110 `"
b10111011001000111111000101110110 e"
b10111011001000111111000101110110 j"
b101 p"
1"
#110000
0"
#115000
b1000100110111000000111010001001 4"
b0 #
b1000011010111001011110110000110100000000000000000000000000000000000000000000000000000000000000000000000000000000000000000000000000000000000000000000000000000000101110110010001111110001011101100000000000000000000000000000000000000000000000000000000000000000100000001111001111100011000000010000000000000000000000000000000000000000000000000000000000000000000000000000000000000000000000000000000000000000000000000000000000000000000000000000000000000000000000000000000000000000000000000000000000000000000000000000000000000000000000000000000000000000100100100001010100110101001001000000010010000100110101100000100100000000000000000000000000000000000000000000000000000000000000000000000000000000000000000000000000000000000000000000000000000000001100101100001010000100011001010000000000000000000000000000000000000000000000000000000000000000 !
b1000011010111001011110110000110100000000000000000000000000000000000000000000000000000000000000000000000000000000000000000000000000000000000000000000000000000000101110110010001111110001011101100000000000000000000000000000000000000000000000000000000000000000100000001111001111100011000000010000000000000000000000000000000000000000000000000000000000000000000000000000000000000000000000000000000000000000000000000000000000000000000000000000000000000000000000000000000000000000000000000000000000000000000000000000000000000000000000000000000000000000100100100001010100110101001001000000010010000100110101100000100100000000000000000000000000000000000000000000000000000000000000000000000000000000000000000000000000000000000000000000000000000000001100101100001010000100011001010000000000000000000000000000000000000000000000000000000000000000 *
b10111011001000111111000101110110 6"
05"
0'
1"
#120000
0"
