pc/prog_counter/pc_mux.v
`timescale 1ns/1ps
module pc_mux(
    input [31:0] pc_next,
    input [31:0] pc_target,
    input pc_src,
    output reg [31:0] pc_mux_out
);
always @(*) begin
    case(pc_src)
        1'b0: pc_mux_out = pc_next;
        1'b1: pc_mux_out = pc_target;
        default: pc_mux_out = pc_next;
    endcase
end
endmodule

pc/pc_blocks/pc_adder/pc_adder.v
`timescale 1ns/1ps
module pc_adder(
    input [31:0] pc_current,
    input [31:0] pc_imm,
    output [31:0] pc_target
);

assign pc_target = pc_current + pc_imm;

endmodule

pc/prog_counter/pc_4.v
module pc_plus_4 (
    input  [31:0] pc,
    output [31:0] pc_plus_4
);
    assign pc_plus_4 = pc + 32'd4;
endmodule

pc/prog_counter/pc_reg.v
`timescale 1ns/1ps
module pc_reg(
    input clk,
    input rst,
    input [31:0] pc_next,
    output reg [31:0] pc_out
);
always @(posedge clk or posedge rst) begin
    if(rst)
        pc_out <= 32'h0000_0000;
    else
        pc_out <= pc_next;
end
endmodule

pc/prog_counter/prog_counter.v
`timescale 1ns/1ps
module prog_counter(
    input clk,
    input rst,
    input pc_src,
    input [31:0] imm_ext,
    output [31:0] pc_out
);

wire [31:0] pc_mux_out;
wire [31:0] pc_plus_4;
wire [31:0] pc_target;
wire [31:0] pc_current;

pc_reg DUT1 (
    .clk(clk),
    .rst(rst),
    .pc_next(pc_mux_out),
    .pc_out(pc_current)
);

pc_plus_4 DUT2 (
    .pc(pc_current),
    .pc_plus_4(pc_plus_4)
);

pc_adder DUT3 (
    .pc_current(pc_current),
    .pc_imm(imm_ext),
    .pc_target(pc_target)
);

pc_mux DUT4 (
    .pc_next(pc_plus_4),
    .pc_target(pc_target),
    .pc_src(pc_src),
    .pc_mux_out(pc_mux_out)
);

assign pc_out = pc_current;

endmodule

pc/prog_counter/prog_counter_tb.v
`timescale 1ns/1ps
module pc_tb();
reg clk;
reg rst;
reg pc_src;
reg [31:0] imm_ext;
wire [31:0] pc_out;

prog_counter DUT (
    .clk(clk),
    .rst(rst),
    .pc_src(pc_src),
    .imm_ext(imm_ext),
    .pc_out(pc_out)
);

initial clk = 0;
always #5 clk = ~clk;

initial begin

    $dumpfile("sim.vcd");
    $dumpvars(0,pc_tb);
    $monitor("Time = %t | clk = %b | rst = %b | pc_src = %b | imm_ext = %h | pc_out = %b", $time, clk, rst, pc_src, imm_ext, pc_out);

    rst = 1;
    pc_src = 0;
    imm_ext = 0;
    #10 
    rst = 0;
    #10;
    //pc+4
    #20;
    pc_src = 0;
    #50;
    //branching or jump statement
    pc_src = 1;
    imm_ext = 32'h0000_0010; 
    #50;
    //branching with different immediate
    imm_ext = 32'h0000_0020;
    #50;
    pc_src = 0;
    #50;
    $finish;
end

endmodule

pc/prog_counter/sim.vcd
$date
	Sat Apr 11 18:15:16 2026
$end
$version
	Icarus Verilog
$end
$timescale
	1ps
$end
$scope module pc_tb $end
$var wire 32 ! pc_out [31:0] $end
$var reg 1 " clk $end
$var reg 32 # imm_ext [31:0] $end
$var reg 1 $ pc_src $end
$var reg 1 % rst $end
$scope module DUT $end
$var wire 1 " clk $end
$var wire 32 & imm_ext [31:0] $end
$var wire 32 ' pc_out [31:0] $end
$var wire 1 $ pc_src $end
$var wire 1 % rst $end
$var wire 32 ( pc_target [31:0] $end
$var wire 32 ) pc_plus_4 [31:0] $end
$var wire 32 * pc_mux_out [31:0] $end
$var wire 32 + pc_current [31:0] $end
$scope module DUT1 $end
$var wire 1 " clk $end
$var wire 1 % rst $end
$var wire 32 , pc_next [31:0] $end
$var reg 32 - pc_out [31:0] $end
$upscope $end
$scope module DUT2 $end
$var wire 32 . pc [31:0] $end
$var wire 32 / pc_plus_4 [31:0] $end
$upscope $end
$scope module DUT3 $end
$var wire 32 0 pc_current [31:0] $end
$var wire 32 1 pc_imm [31:0] $end
$var wire 32 2 pc_target [31:0] $end
$upscope $end
$scope module DUT4 $end
$var wire 32 3 pc_next [31:0] $end
$var wire 1 $ pc_src $end
$var wire 32 4 pc_target [31:0] $end
$var reg 32 5 pc_mux_out [31:0] $end
$upscope $end
$upscope $end
$upscope $end
$enddefinitions $end
$comment Show the parameter values. $end
$dumpall
$end
#0
$dumpvars
b100 5
b0 4
b100 3
b0 2
b0 1
b0 0
b100 /
b0 .
b0 -
b100 ,
b0 +
b100 *
b100 )
b0 (
b0 '
b0 &
1%
0$
b0 #
0"
b0 !
$end
#5000
1"
#10000
0"
0%
#15000
b1000 *
b1000 ,
b1000 5
b1000 )
b1000 /
b1000 3
b100 (
b100 2
b100 4
b100 !
b100 '
b100 +
b100 -
b100 .
b100 0
1"
#20000
0"
#25000
b1100 *
b1100 ,
b1100 5
b1100 )
b1100 /
b1100 3
b1000 (
b1000 2
b1000 4
b1000 !
b1000 '
b1000 +
b1000 -
b1000 .
b1000 0
1"
#30000
0"
#35000
b10000 *
b10000 ,
b10000 5
b10000 )
b10000 /
b10000 3
b1100 (
b1100 2
b1100 4
b1100 !
b1100 '
b1100 +
b1100 -
b1100 .
b1100 0
1"
#40000
0"
#45000
b10100 *
b10100 ,
b10100 5
b10100 )
b10100 /
b10100 3
b10000 (
b10000 2
b10000 4
b10000 !
b10000 '
b10000 +
b10000 -
b10000 .
b10000 0
1"
#50000
0"
#55000
b11000 *
b11000 ,
b11000 5
b11000 )
b11000 /
b11000 3
b10100 (
b10100 2
b10100 4
b10100 !
b10100 '
b10100 +
b10100 -
b10100 .
b10100 0
1"
#60000
0"
#65000
b11100 *
b11100 ,
b11100 5
b11100 )
b11100 /
b11100 3
b11000 (
b11000 2
b11000 4
b11000 !
b11000 '
b11000 +
b11000 -
b11000 .
b11000 0
1"
#70000
0"
#75000
b100000 *
b100000 ,
b100000 5
b100000 )
b100000 /
b100000 3
b11100 (
b11100 2
b11100 4
b11100 !
b11100 '
b11100 +
b11100 -
b11100 .
b11100 0
1"
#80000
0"
#85000
b100100 *
b100100 ,
b100100 5
b100100 )
b100100 /
b100100 3
b100000 (
b100000 2
b100000 4
b100000 !
b100000 '
b100000 +
b100000 -
b100000 .
b100000 0
1"
#90000
b110000 *
b110000 ,
b110000 5
0"
b110000 (
b110000 2
b110000 4
b10000 #
b10000 &
b10000 1
1$
#95000
b1000000 *
b1000000 ,
b1000000 5
b110100 )
b110100 /
b110100 3
b1000000 (
b1000000 2
b1000000 4
b110000 !
b110000 '
b110000 +
b110000 -
b110000 .
b110000 0
1"
#100000
0"
#105000
b1010000 *
b1010000 ,
b1010000 5
b1000100 )
b1000100 /
b1000100 3
b1010000 (
b1010000 2
b1010000 4
b1000000 !
b1000000 '
b1000000 +
b1000000 -
b1000000 .
b1000000 0
1"
#110000
0"
#115000
b1100000 *
b1100000 ,
b1100000 5
b1010100 )
b1010100 /
b1010100 3
b1100000 (
b1100000 2
b1100000 4
b1010000 !
b1010000 '
b1010000 +
b1010000 -
b1010000 .
b1010000 0
1"
#120000
0"
#125000
b1110000 *
b1110000 ,
b1110000 5
b1100100 )
b1100100 /
b1100100 3
b1110000 (
b1110000 2
b1110000 4
b1100000 !
b1100000 '
b1100000 +
b1100000 -
b1100000 .
b1100000 0
1"
#130000
0"
#135000
b10000000 *
b10000000 ,
b10000000 5
b1110100 )
b1110100 /
b1110100 3
b10000000 (
b10000000 2
b10000000 4
b1110000 !
b1110000 '
b1110000 +
b1110000 -
b1110000 .
b1110000 0
1"
#140000
b10010000 *
b10010000 ,
b10010000 5
0"
b10010000 (
b10010000 2
b10010000 4
b100000 #
b100000 &
b100000 1
#145000
b10110000 *
b10110000 ,
b10110000 5
b10010100 )
b10010100 /
b10010100 3
b10110000 (
b10110000 2
b10110000 4
b10010000 !
b10010000 '
b10010000 +
b10010000 -
b10010000 .
b10010000 0
1"
#150000
0"
#155000
b11010000 *
b11010000 ,
b11010000 5
b10110100 )
b10110100 /
b10110100 3
b11010000 (
b11010000 2
b11010000 4
b10110000 !
b10110000 '
b10110000 +
b10110000 -
b10110000 .
b10110000 0
1"
#160000
0"
#165000
b11110000 *
b11110000 ,
b11110000 5
b11010100 )
b11010100 /
b11010100 3
b11110000 (
b11110000 2
b11110000 4
b11010000 !
b11010000 '
b11010000 +
b11010000 -
b11010000 .
b11010000 0
1"
#170000
0"
#175000
b100010000 *
b100010000 ,
b100010000 5
b11110100 )
b11110100 /
b11110100 3
b100010000 (
b100010000 2
b100010000 4
b11110000 !
b11110000 '
b11110000 +
b11110000 -
b11110000 .
b11110000 0
1"
#180000
0"
#185000
b100110000 *
b100110000 ,
b100110000 5
b100010100 )
b100010100 /
b100010100 3
b100110000 (
b100110000 2
b100110000 4
b100010000 !
b100010000 '
b100010000 +
b100010000 -
b100010000 .
b100010000 0
1"
#190000
b100010100 *
b100010100 ,
b100010100 5
0"
0$
#195000
b100011000 *
b100011000 ,
b100011000 5
b100011000 )
b100011000 /
b100011000 3
b100110100 (
b100110100 2
b100110100 4
b100010100 !
b100010100 '
b100010100 +
b100010100 -
b100010100 .
b100010100 0
1"
#200000
0"
#205000
b100011100 *
b100011100 ,
b100011100 5
b100011100 )
b100011100 /
b100011100 3
b100111000 (
b100111000 2
b100111000 4
b100011000 !
b100011000 '
b100011000 +
b100011000 -
b100011000 .
b100011000 0
1"
#210000
0"
#215000
b100100000 *
b100100000 ,
b100100000 5
b100100000 )
b100100000 /
b100100000 3
b100111100 (
b100111100 2
b100111100 4
b100011100 !
b100011100 '
b100011100 +
b100011100 -
b100011100 .
b100011100 0
1"
#220000
0"
#225000
b100100100 *
b100100100 ,
b100100100 5
b100100100 )
b100100100 /
b100100100 3
b101000000 (
b101000000 2
b101000000 4
b100100000 !
b100100000 '
b100100000 +
b100100000 -
b100100000 .
b100100000 0
1"
#230000
0"
#235000
b100101000 *
b100101000 ,
b100101000 5
b100101000 )
b100101000 /
b100101000 3
b101000100 (
b101000100 2
b101000100 4
b100100100 !
b100100100 '
b100100100 +
b100100100 -
b100100100 .
b100100100 0
1"
