reg_32/regfile/reg_file.sv
`timescale 1ns/1ps
module reg_file(
    input logic clk,
    input logic rst,
    input logic w_en,           //write enable
    input logic [4:0] rs1,      //first input register
    input logic [4:0] rs2,      //second input register 
    input logic [4:0] rd,       //destination register
    input logic [31:0] wr_d,     //write date
    output logic [31:0] rd1,    //output 32 bit     (can read upto 2 registers at a time)
    output logic [31:0] rd2     //output 32 bit
);

logic [31:0] regs [31:0];


assign rd1 = (rs1 == 0) ? 32'b0 : regs[rs1];     //if rs1 value is 0 then return 0 else return reg[rs1]
assign rd2 = (rs2 == 0) ? 32'b0 : regs[rs2];     //if rs2 value is 0 then return 0 else return reg[rs2]

always_ff @(posedge clk or posedge rst) begin
    if (rst) begin                                      //if rst is on, every register is made to 32'b0 value
        integer  i;
        for (i = 0 ; i < 32 ; i = i + 1) begin
            regs[i] = 32'b0;
        end
    end
    else if (w_en && (rd != 0)) begin   //else if write enable is on and destination register address is not 0, destination register is written
        regs[rd] <= wr_d;
    end
end
endmodule

reg_32/regfile/reg_file_tb.sv
`timescale 1ns/1ps
module reg_file_tb();
logic clk;
logic rst;
logic w_en;
logic [4:0] rs1;
logic [4:0] rs2;
logic [4:0] rd;
logic [31:0] wr_d;
logic [31:0] rd1;
logic [31:0] rd2;

reg_file DUT (
    .clk(clk),
    .rst(rst),
    .w_en(w_en),
    .rs1(rs1),
    .rs2(rs2),
    .rd(rd),
    .wr_d(wr_d),
    .rd1(rd1),
    .rd2(rd2)
);

always #5 clk = ~clk;

initial begin
    $dumpfile("sim.vcd");
    $dumpvars(0,reg_file_tb);
    clk = 0;
    rst = 1;
    w_en = 0;
    rs1 = 0;
    rs2 = 0;
    rd  = 0;
    wr_d = 0;

    $dumpfile("sim.vcd");
    $dumpvars(0, reg_file_tb);

    #10;
    rst = 0;

    #10;
    w_en = 1;
    rd = 5'd1;
    wr_d = 32'd10;

    #10;
    w_en = 0;

    #10;
    w_en = 1;
    rd = 5'd2;
    wr_d = 32'd20;

    #10;
    w_en = 0;

    #10;
    rs1 = 5'd1;
    rs2 = 5'd2;

    #10;
    $display("x1 = %d | x2 = %d", rd1, rd2);

    #10;
    w_en = 1;
    rd = 5'd0;
    wr_d = 32'd999;

    #10;
    w_en = 0;
    rs1 = 5'd0;

    #10;
    $display("x0 = %d", rd1);

    #20;
    $finish;

end
endmodule

reg_32/regfile/sim.vcd
$date
	Mon Apr 20 21:52:18 2026
$end
$version
	Icarus Verilog
$end
$timescale
	1ps
$end
$scope module reg_file_tb $end
$var wire 32 ! rd2 [31:0] $end
$var wire 32 " rd1 [31:0] $end
$var reg 1 # clk $end
$var reg 5 $ rd [4:0] $end
$var reg 5 % rs1 [4:0] $end
$var reg 5 & rs2 [4:0] $end
$var reg 1 ' rst $end
$var reg 1 ( w_en $end
$var reg 32 ) wr_d [31:0] $end
$scope module DUT $end
$var wire 1 # clk $end
$var wire 5 * rd [4:0] $end
$var wire 5 + rs1 [4:0] $end
$var wire 5 , rs2 [4:0] $end
$var wire 1 ' rst $end
$var wire 1 ( w_en $end
$var wire 32 - wr_d [31:0] $end
$var wire 32 . rd2 [31:0] $end
$var wire 32 / rd1 [31:0] $end
$scope begin $unm_blk_2 $end
$var integer 32 0 i [31:0] $end
$upscope $end
$upscope $end
$upscope $end
$scope module reg_file_tb $end
$scope module DUT $end
$scope begin $unm_blk_2 $end
$upscope $end
$upscope $end
$upscope $end
$enddefinitions $end
$comment Show the parameter values. $end
$dumpall
$end
#0
$dumpvars
b100000 0
b0 /
b0 .
b0 -
b0 ,
b0 +
b0 *
b0 )
0(
1'
b0 &
b0 %
b0 $
0#
b0 "
b0 !
$end
#5000
b100000 0
1#
#10000
0#
0'
#15000
1#
#20000
0#
b1010 )
b1010 -
b1 $
b1 *
1(
#25000
1#
#30000
0#
0(
#35000
1#
#40000
0#
b10100 )
b10100 -
b10 $
b10 *
1(
#45000
1#
#50000
0#
0(
#55000
1#
#60000
b10100 !
b10100 .
b1010 "
b1010 /
0#
b10 &
b10 ,
b1 %
b1 +
#65000
1#
#70000
0#
#75000
1#
#80000
0#
b1111100111 )
b1111100111 -
b0 $
b0 *
1(
#85000
1#
#90000
b0 "
b0 /
0#
b0 %
b0 +
0(
