control_unit/c_unit.v
`timescale 1ns/1ps
module cntrl_unit(
    input [31:0] instr,
    input zero,
    input negative,
    input carry,
    input overflow,
    input rst,
    input clk, 
    output reg [3:0] alu_ctrl,
    output reg reg_write,
    output reg mem_read,
    output reg mem_write,
    output reg alu_src,
    output reg branch,
    output reg jump,
    output reg [1:0] wb_sel,
    output reg [2:0] imm_sel
);

wire [6:0] opcode;
wire [2:0] funct3 = instr[14:12];
wire [6:0] funct7 = instr[31:25];
assign opcode = instr[6:0];

always @(*) begin
    alu_ctrl = 4'b0000;
    reg_write = 1'b0;
    mem_read = 1'b0;
    mem_write = 1'b0;
    alu_src = 1'b0;
    branch = 1'b0;
    jump = 1'b0;
    wb_sel = 2'b00;
    imm_sel = 3'b000;
    case(opcode)
        //R-TYPE INSTRUCTIONS
        7'b0110011: begin
            reg_write = 1'b1;   //writing result to register
            alu_src = 1'b0;     //using rs2 value
            wb_sel = 2'b00;     //written back
            case({funct7,funct3})
                10'b0000000_000: alu_ctrl = 4'b0000;    //addition
                10'b0100000_000: alu_ctrl = 4'b0001;    //subtraction
                10'b0000000_001: alu_ctrl = 4'b0101;    //logical left shift
                10'b0000000_010: alu_ctrl = 4'b0110;    //set less than (signed)
                10'b0000000_011: alu_ctrl = 4'b0111;    //set less than (unsigned)
                10'b0000000_100: alu_ctrl = 4'b0100;    //xor
                10'b0000000_101: alu_ctrl = 4'b1000;    //logical right shift
                10'b0100000_101: alu_ctrl = 4'b1001;    //arithmatic right shift
                10'b0000000_110: alu_ctrl = 4'b0011;    //logical or
                10'b0000000_111: alu_ctrl = 4'b0010;    //logical and
                default: alu_ctrl = 4'b0000;            //default case addition
            endcase
        end
        
        //I-TYPE INSTRUCTIONS
        7'b0010011: begin
            reg_write = 1'b1;       //writing result to register
            alu_src = 1'b1;         //using rs2 value
            wb_sel = 2'b00;         //written back
            imm_sel = 3'b000;

            case(funct3)
                3'b000: alu_ctrl = 4'b0000; //addi
                3'b111: alu_ctrl = 4'b0010; //andi
                3'b110: alu_ctrl = 4'b0011; //ori
                3'b100: alu_ctrl = 4'b0100; //xori
                3'b001: alu_ctrl = 4'b0101; //shift left by immediate
                3'b101: alu_ctrl = (instr[30]) ? 4'b1001 : 4'b1000; //shift right arithmetic / logical by immediate
                default: alu_ctrl = 4'b0000;
            endcase
        end

        //S-TYPE INSTRUCTIONS
        //LOAD-WORD (lw)
        7'b0000011: begin
            reg_write = 1'b1;   //saving to register
            mem_read = 1'b1;    //writing to memory
            alu_src = 1'b1;     //alu looks for immediate
            wb_sel = 2'b01;     //writing bag
            imm_sel = 3'b000;   //imm gen uses s type logic
            alu_ctrl = 4'b0000; //adding operation
        end
        //STORE-WORD (sw)
        7'b0100011: begin
            mem_write = 1;          //writing to memory
            alu_src   = 1;          //using rs2
            imm_sel   = 3'b001;     //S-type instructions
            alu_ctrl  = 4'b0000;    //alu performs addition
        end

        //B-TYPE INSTRUCTIONS
        7'b1100011: begin
            branch = 1'b1;      //enables branch
            alu_src = 1'b0;     //uses imm_value (offset)
            imm_sel = 3'b010;   //B-type instructions
            case(funct3)
                3'b000: alu_ctrl = 4'b0001;     //branch if equal
                3'b001: alu_ctrl = 4'b0001;     //branch if not equal
                default: alu_ctrl = 4'b0001;    //default value is set to subraction
            endcase
        end

        //U-TYPE INSTRUCTIONS
        //Load Upper Immediate
        7'b0110111: begin
            reg_write = 1'b1;
            alu_src = 1'b0;
            wb_sel = 2'b11;
            imm_sel = 3'b011;
        end
        //Add Upper Immediate to PC
        7'b0010111: begin
            reg_write = 1'b1;  
            alu_src   = 1'b1;  
            wb_sel    = 2'b00; 
            imm_sel   = 3'b011;
            alu_ctrl  = 4'b0000;
        end

        7'b1101111: begin
            jump      = 1'b1;   
            reg_write = 1'b1;   
            wb_sel    = 2'b10;  
            imm_sel   = 3'b100; 
            alu_src   = 1'b0;   
        end
    endcase
end
endmodule

control_unit/c_unit_tb.v
`timescale 1ns/1ps

module cntrl_unit_tb;

reg [31:0] instr;
reg zero;
reg negative;
reg carry;
reg overflow;
reg rst;
reg clk;

wire [3:0] alu_ctrl;
wire reg_write;
wire mem_read;
wire mem_write;
wire alu_src;
wire branch;
wire jump;
wire [1:0] wb_sel;
wire [2:0] imm_sel;

cntrl_unit dut (
    .instr(instr),
    .zero(zero),
    .negative(negative),
    .carry(carry),
    .overflow(overflow),
    .rst(rst),
    .clk(clk),
    .alu_ctrl(alu_ctrl),
    .reg_write(reg_write),
    .mem_read(mem_read),
    .mem_write(mem_write),
    .alu_src(alu_src),
    .branch(branch),
    .jump(jump),
    .wb_sel(wb_sel),
    .imm_sel(imm_sel)
);

always #5 clk = ~clk;

task apply_instr(input [31:0] inst);
begin
    instr = inst;
    #10;
end
endtask

initial begin
    $dumpfile("cntrl_unit.vcd");
    $dumpvars(0, cntrl_unit_tb);

    clk = 0;
    rst = 1;
    instr = 0;
    zero = 0;
    negative = 0;
    carry = 0;
    overflow = 0;

    #10 rst = 0;

    apply_instr(32'b0000000_00000_00000_000_00000_0110011);
    apply_instr(32'b0100000_00000_00000_000_00000_0110011);
    apply_instr(32'b0000000_00000_00000_111_00000_0110011);

    apply_instr(32'b000000000001_00000_000_00000_0010011);

    apply_instr(32'b000000000001_00000_010_00000_0000011);

    apply_instr(32'b0000000_00000_00000_010_00000_0100011);

    zero = 1;
    apply_instr(32'b0000000_00000_00000_000_00000_1100011);
    zero = 0;

    apply_instr(32'b00000000000000000000_00000_0110111);
    apply_instr(32'b00000000000000000000_00000_0010111);

    apply_instr(32'b00000000000000000000_00000_1101111);

    #20;
    $finish;
end

endmodule

control_unit/cntrl_unit.vcd
$date
	Thu Apr 16 11:06:04 2026
$end
$version
	Icarus Verilog
$end
$timescale
	1ps
$end
$scope module cntrl_unit_tb $end
$var wire 2 ! wb_sel [1:0] $end
$var wire 1 " reg_write $end
$var wire 1 # mem_write $end
$var wire 1 $ mem_read $end
$var wire 1 % jump $end
$var wire 3 & imm_sel [2:0] $end
$var wire 1 ' branch $end
$var wire 1 ( alu_src $end
$var wire 4 ) alu_ctrl [3:0] $end
$var reg 1 * carry $end
$var reg 1 + clk $end
$var reg 32 , instr [31:0] $end
$var reg 1 - negative $end
$var reg 1 . overflow $end
$var reg 1 / rst $end
$var reg 1 0 zero $end
$scope module dut $end
$var wire 1 * carry $end
$var wire 1 + clk $end
$var wire 32 1 instr [31:0] $end
$var wire 1 - negative $end
$var wire 1 . overflow $end
$var wire 1 / rst $end
$var wire 1 0 zero $end
$var wire 7 2 opcode [6:0] $end
$var wire 7 3 funct7 [6:0] $end
$var wire 3 4 funct3 [2:0] $end
$var reg 4 5 alu_ctrl [3:0] $end
$var reg 1 ( alu_src $end
$var reg 1 ' branch $end
$var reg 3 6 imm_sel [2:0] $end
$var reg 1 % jump $end
$var reg 1 $ mem_read $end
$var reg 1 # mem_write $end
$var reg 1 " reg_write $end
$var reg 2 7 wb_sel [1:0] $end
$upscope $end
$scope task apply_instr $end
$var reg 32 8 inst [31:0] $end
$upscope $end
$upscope $end
$enddefinitions $end
$comment Show the parameter values. $end
$dumpall
$end
#0
$dumpvars
bx 8
b0 7
b0 6
b0 5
b0 4
b0 3
b0 2
b0 1
00
1/
0.
0-
b0 ,
0+
0*
b0 )
0(
0'
b0 &
0%
0$
0#
0"
b0 !
$end
#5000
1+
#10000
1"
b110011 2
0+
b110011 ,
b110011 1
b110011 8
0/
#15000
1+
#20000
b1 )
b1 5
1"
b100000 3
0+
b1000000000000000000000000110011 ,
b1000000000000000000000000110011 1
b1000000000000000000000000110011 8
#25000
1+
#30000
1"
b10 )
b10 5
b111 4
b0 3
0+
b111000000110011 ,
b111000000110011 1
b111000000110011 8
#35000
1+
#40000
1(
1"
b0 )
b0 5
b0 4
b10011 2
0+
b100000000000000010011 ,
b100000000000000010011 1
b100000000000000010011 8
#45000
1+
#50000
b1 !
b1 7
1$
1(
1"
b10 4
b11 2
0+
b100000010000000000011 ,
b100000010000000000011 1
b100000010000000000011 8
#55000
1+
#60000
b1 &
b1 6
1#
b0 !
b0 7
1(
0$
0"
b100011 2
0+
b10000000100011 ,
b10000000100011 1
b10000000100011 8
#65000
1+
#70000
b1 )
b1 5
1'
b10 &
b10 6
0(
0#
b0 4
b1100011 2
0+
b1100011 ,
b1100011 1
b1100011 8
10
#75000
1+
#80000
b11 !
b11 7
1"
b11 &
b11 6
0'
b0 )
b0 5
b110111 2
0+
b110111 ,
b110111 1
b110111 8
00
#85000
1+
#90000
1(
b11 &
b11 6
b0 !
b0 7
1"
b10111 2
0+
b10111 ,
b10111 1
b10111 8
#95000
1+
#100000
b10 !
b10 7
1%
b100 &
b100 6
0(
1"
b1101111 2
0+
b1101111 ,
b1101111 1
b1101111 8
