reg_32/reg_blocks/mux32/mux32.sv
`timescale 1ns/1ps
module mux32(
    input [31:0][31:0]din, //our mux needs to take 32 bit inputs from 32 registers
    input [4:0]sel,
    output reg [31:0]dout
);
always @(*) begin
    dout = din[sel];
end
endmodule

reg_32/reg_blocks/mux32/mux32_tb.sv
`timescale 1ns/1ps
module mux32_tb();
reg [31:0][31:0]din_tb;
reg [4:0]sel_tb;
wire [31:0]dout_tb;

mux32 uut(
    .din(din_tb),
    .sel(sel_tb),
    .dout(dout_tb)
);

initial begin
    $dumpfile("sim.vcd");
    $dumpvars(0,mux32_tb);
    $monitor("Time = %t | reg = %d | value = %d", $time, sel_tb, dout_tb);
    for (integer i = 0; i < 32; i = i + 1) begin
        din_tb[i] = i + 1;
        sel_tb = i;
        #10;
    end
end
endmodule

reg_32/reg_blocks/mux32/sim.vcd
$date
	Mon Mar 30 19:58:56 2026
$end
$version
	Icarus Verilog
$end
$timescale
	1ps
$end
$scope module mux32_tb $end
$var wire 32 ! dout_tb [31:0] $end
$var reg 1024 " din_tb [1023:0] $end
$var reg 5 # sel_tb [4:0] $end
$scope module uut $end
$var wire 1024 $ din [1023:0] $end
$var wire 5 % sel [4:0] $end
$var reg 32 & dout [31:0] $end
$upscope $end
$scope begin $ivl_for_loop0 $end
$var integer 32 ' i [31:0] $end
$upscope $end
$upscope $end
$enddefinitions $end
$comment Show the parameter values. $end
$dumpall
$end
#0
$dumpvars
b0 '
b1 &
b0 %
bx00000000000000000000000000000001 $
b0 #
bx00000000000000000000000000000001 "
b1 !
$end
#10000
b10 !
b10 &
b1 #
b1 %
bx0000000000000000000000000000001000000000000000000000000000000001 "
bx0000000000000000000000000000001000000000000000000000000000000001 $
b1 '
#20000
b11 !
b11 &
b10 #
b10 %
bx000000000000000000000000000000110000000000000000000000000000001000000000000000000000000000000001 "
bx000000000000000000000000000000110000000000000000000000000000001000000000000000000000000000000001 $
b10 '
#30000
b100 !
b100 &
b11 #
b11 %
bx00000000000000000000000000000100000000000000000000000000000000110000000000000000000000000000001000000000000000000000000000000001 "
bx00000000000000000000000000000100000000000000000000000000000000110000000000000000000000000000001000000000000000000000000000000001 $
b11 '
#40000
b101 !
b101 &
b100 #
b100 %
bx0000000000000000000000000000010100000000000000000000000000000100000000000000000000000000000000110000000000000000000000000000001000000000000000000000000000000001 "
bx0000000000000000000000000000010100000000000000000000000000000100000000000000000000000000000000110000000000000000000000000000001000000000000000000000000000000001 $
b100 '
#50000
b110 !
b110 &
b101 #
b101 %
bx000000000000000000000000000001100000000000000000000000000000010100000000000000000000000000000100000000000000000000000000000000110000000000000000000000000000001000000000000000000000000000000001 "
bx000000000000000000000000000001100000000000000000000000000000010100000000000000000000000000000100000000000000000000000000000000110000000000000000000000000000001000000000000000000000000000000001 $
b101 '
#60000
b111 !
b111 &
b110 #
b110 %
bx00000000000000000000000000000111000000000000000000000000000001100000000000000000000000000000010100000000000000000000000000000100000000000000000000000000000000110000000000000000000000000000001000000000000000000000000000000001 "
bx00000000000000000000000000000111000000000000000000000000000001100000000000000000000000000000010100000000000000000000000000000100000000000000000000000000000000110000000000000000000000000000001000000000000000000000000000000001 $
b110 '
#70000
b1000 !
b1000 &
b111 #
b111 %
bx0000000000000000000000000000100000000000000000000000000000000111000000000000000000000000000001100000000000000000000000000000010100000000000000000000000000000100000000000000000000000000000000110000000000000000000000000000001000000000000000000000000000000001 "
bx0000000000000000000000000000100000000000000000000000000000000111000000000000000000000000000001100000000000000000000000000000010100000000000000000000000000000100000000000000000000000000000000110000000000000000000000000000001000000000000000000000000000000001 $
b111 '
#80000
b1001 !
b1001 &
b1000 #
b1000 %
bx000000000000000000000000000010010000000000000000000000000000100000000000000000000000000000000111000000000000000000000000000001100000000000000000000000000000010100000000000000000000000000000100000000000000000000000000000000110000000000000000000000000000001000000000000000000000000000000001 "
bx000000000000000000000000000010010000000000000000000000000000100000000000000000000000000000000111000000000000000000000000000001100000000000000000000000000000010100000000000000000000000000000100000000000000000000000000000000110000000000000000000000000000001000000000000000000000000000000001 $
b1000 '
#90000
b1010 !
b1010 &
b1001 #
b1001 %
bx00000000000000000000000000001010000000000000000000000000000010010000000000000000000000000000100000000000000000000000000000000111000000000000000000000000000001100000000000000000000000000000010100000000000000000000000000000100000000000000000000000000000000110000000000000000000000000000001000000000000000000000000000000001 "
bx00000000000000000000000000001010000000000000000000000000000010010000000000000000000000000000100000000000000000000000000000000111000000000000000000000000000001100000000000000000000000000000010100000000000000000000000000000100000000000000000000000000000000110000000000000000000000000000001000000000000000000000000000000001 $
b1001 '
#100000
b1011 !
b1011 &
b1010 #
b1010 %
bx0000000000000000000000000000101100000000000000000000000000001010000000000000000000000000000010010000000000000000000000000000100000000000000000000000000000000111000000000000000000000000000001100000000000000000000000000000010100000000000000000000000000000100000000000000000000000000000000110000000000000000000000000000001000000000000000000000000000000001 "
bx0000000000000000000000000000101100000000000000000000000000001010000000000000000000000000000010010000000000000000000000000000100000000000000000000000000000000111000000000000000000000000000001100000000000000000000000000000010100000000000000000000000000000100000000000000000000000000000000110000000000000000000000000000001000000000000000000000000000000001 $
b1010 '
#110000
b1100 !
b1100 &
b1011 #
b1011 %
bx000000000000000000000000000011000000000000000000000000000000101100000000000000000000000000001010000000000000000000000000000010010000000000000000000000000000100000000000000000000000000000000111000000000000000000000000000001100000000000000000000000000000010100000000000000000000000000000100000000000000000000000000000000110000000000000000000000000000001000000000000000000000000000000001 "
bx000000000000000000000000000011000000000000000000000000000000101100000000000000000000000000001010000000000000000000000000000010010000000000000000000000000000100000000000000000000000000000000111000000000000000000000000000001100000000000000000000000000000010100000000000000000000000000000100000000000000000000000000000000110000000000000000000000000000001000000000000000000000000000000001 $
b1011 '
#120000
b1101 !
b1101 &
b1100 #
b1100 %
bx00000000000000000000000000001101000000000000000000000000000011000000000000000000000000000000101100000000000000000000000000001010000000000000000000000000000010010000000000000000000000000000100000000000000000000000000000000111000000000000000000000000000001100000000000000000000000000000010100000000000000000000000000000100000000000000000000000000000000110000000000000000000000000000001000000000000000000000000000000001 "
bx00000000000000000000000000001101000000000000000000000000000011000000000000000000000000000000101100000000000000000000000000001010000000000000000000000000000010010000000000000000000000000000100000000000000000000000000000000111000000000000000000000000000001100000000000000000000000000000010100000000000000000000000000000100000000000000000000000000000000110000000000000000000000000000001000000000000000000000000000000001 $
b1100 '
#130000
b1110 !
b1110 &
b1101 #
b1101 %
bx0000000000000000000000000000111000000000000000000000000000001101000000000000000000000000000011000000000000000000000000000000101100000000000000000000000000001010000000000000000000000000000010010000000000000000000000000000100000000000000000000000000000000111000000000000000000000000000001100000000000000000000000000000010100000000000000000000000000000100000000000000000000000000000000110000000000000000000000000000001000000000000000000000000000000001 "
bx0000000000000000000000000000111000000000000000000000000000001101000000000000000000000000000011000000000000000000000000000000101100000000000000000000000000001010000000000000000000000000000010010000000000000000000000000000100000000000000000000000000000000111000000000000000000000000000001100000000000000000000000000000010100000000000000000000000000000100000000000000000000000000000000110000000000000000000000000000001000000000000000000000000000000001 $
b1101 '
#140000
b1111 !
b1111 &
b1110 #
b1110 %
bx000000000000000000000000000011110000000000000000000000000000111000000000000000000000000000001101000000000000000000000000000011000000000000000000000000000000101100000000000000000000000000001010000000000000000000000000000010010000000000000000000000000000100000000000000000000000000000000111000000000000000000000000000001100000000000000000000000000000010100000000000000000000000000000100000000000000000000000000000000110000000000000000000000000000001000000000000000000000000000000001 "
bx000000000000000000000000000011110000000000000000000000000000111000000000000000000000000000001101000000000000000000000000000011000000000000000000000000000000101100000000000000000000000000001010000000000000000000000000000010010000000000000000000000000000100000000000000000000000000000000111000000000000000000000000000001100000000000000000000000000000010100000000000000000000000000000100000000000000000000000000000000110000000000000000000000000000001000000000000000000000000000000001 $
b1110 '
#150000
b10000 !
b10000 &
b1111 #
b1111 %
bx00000000000000000000000000010000000000000000000000000000000011110000000000000000000000000000111000000000000000000000000000001101000000000000000000000000000011000000000000000000000000000000101100000000000000000000000000001010000000000000000000000000000010010000000000000000000000000000100000000000000000000000000000000111000000000000000000000000000001100000000000000000000000000000010100000000000000000000000000000100000000000000000000000000000000110000000000000000000000000000001000000000000000000000000000000001 "
bx00000000000000000000000000010000000000000000000000000000000011110000000000000000000000000000111000000000000000000000000000001101000000000000000000000000000011000000000000000000000000000000101100000000000000000000000000001010000000000000000000000000000010010000000000000000000000000000100000000000000000000000000000000111000000000000000000000000000001100000000000000000000000000000010100000000000000000000000000000100000000000000000000000000000000110000000000000000000000000000001000000000000000000000000000000001 $
b1111 '
#160000
b10001 !
b10001 &
b10000 #
b10000 %
bx0000000000000000000000000001000100000000000000000000000000010000000000000000000000000000000011110000000000000000000000000000111000000000000000000000000000001101000000000000000000000000000011000000000000000000000000000000101100000000000000000000000000001010000000000000000000000000000010010000000000000000000000000000100000000000000000000000000000000111000000000000000000000000000001100000000000000000000000000000010100000000000000000000000000000100000000000000000000000000000000110000000000000000000000000000001000000000000000000000000000000001 "
bx0000000000000000000000000001000100000000000000000000000000010000000000000000000000000000000011110000000000000000000000000000111000000000000000000000000000001101000000000000000000000000000011000000000000000000000000000000101100000000000000000000000000001010000000000000000000000000000010010000000000000000000000000000100000000000000000000000000000000111000000000000000000000000000001100000000000000000000000000000010100000000000000000000000000000100000000000000000000000000000000110000000000000000000000000000001000000000000000000000000000000001 $
b10000 '
#170000
b10010 !
b10010 &
b10001 #
b10001 %
bx000000000000000000000000000100100000000000000000000000000001000100000000000000000000000000010000000000000000000000000000000011110000000000000000000000000000111000000000000000000000000000001101000000000000000000000000000011000000000000000000000000000000101100000000000000000000000000001010000000000000000000000000000010010000000000000000000000000000100000000000000000000000000000000111000000000000000000000000000001100000000000000000000000000000010100000000000000000000000000000100000000000000000000000000000000110000000000000000000000000000001000000000000000000000000000000001 "
bx000000000000000000000000000100100000000000000000000000000001000100000000000000000000000000010000000000000000000000000000000011110000000000000000000000000000111000000000000000000000000000001101000000000000000000000000000011000000000000000000000000000000101100000000000000000000000000001010000000000000000000000000000010010000000000000000000000000000100000000000000000000000000000000111000000000000000000000000000001100000000000000000000000000000010100000000000000000000000000000100000000000000000000000000000000110000000000000000000000000000001000000000000000000000000000000001 $
b10001 '
#180000
b10011 !
b10011 &
b10010 #
b10010 %
bx00000000000000000000000000010011000000000000000000000000000100100000000000000000000000000001000100000000000000000000000000010000000000000000000000000000000011110000000000000000000000000000111000000000000000000000000000001101000000000000000000000000000011000000000000000000000000000000101100000000000000000000000000001010000000000000000000000000000010010000000000000000000000000000100000000000000000000000000000000111000000000000000000000000000001100000000000000000000000000000010100000000000000000000000000000100000000000000000000000000000000110000000000000000000000000000001000000000000000000000000000000001 "
bx00000000000000000000000000010011000000000000000000000000000100100000000000000000000000000001000100000000000000000000000000010000000000000000000000000000000011110000000000000000000000000000111000000000000000000000000000001101000000000000000000000000000011000000000000000000000000000000101100000000000000000000000000001010000000000000000000000000000010010000000000000000000000000000100000000000000000000000000000000111000000000000000000000000000001100000000000000000000000000000010100000000000000000000000000000100000000000000000000000000000000110000000000000000000000000000001000000000000000000000000000000001 $
b10010 '
#190000
b10100 !
b10100 &
b10011 #
b10011 %
bx0000000000000000000000000001010000000000000000000000000000010011000000000000000000000000000100100000000000000000000000000001000100000000000000000000000000010000000000000000000000000000000011110000000000000000000000000000111000000000000000000000000000001101000000000000000000000000000011000000000000000000000000000000101100000000000000000000000000001010000000000000000000000000000010010000000000000000000000000000100000000000000000000000000000000111000000000000000000000000000001100000000000000000000000000000010100000000000000000000000000000100000000000000000000000000000000110000000000000000000000000000001000000000000000000000000000000001 "
bx0000000000000000000000000001010000000000000000000000000000010011000000000000000000000000000100100000000000000000000000000001000100000000000000000000000000010000000000000000000000000000000011110000000000000000000000000000111000000000000000000000000000001101000000000000000000000000000011000000000000000000000000000000101100000000000000000000000000001010000000000000000000000000000010010000000000000000000000000000100000000000000000000000000000000111000000000000000000000000000001100000000000000000000000000000010100000000000000000000000000000100000000000000000000000000000000110000000000000000000000000000001000000000000000000000000000000001 $
b10011 '
#200000
b10101 !
b10101 &
b10100 #
b10100 %
bx000000000000000000000000000101010000000000000000000000000001010000000000000000000000000000010011000000000000000000000000000100100000000000000000000000000001000100000000000000000000000000010000000000000000000000000000000011110000000000000000000000000000111000000000000000000000000000001101000000000000000000000000000011000000000000000000000000000000101100000000000000000000000000001010000000000000000000000000000010010000000000000000000000000000100000000000000000000000000000000111000000000000000000000000000001100000000000000000000000000000010100000000000000000000000000000100000000000000000000000000000000110000000000000000000000000000001000000000000000000000000000000001 "
bx000000000000000000000000000101010000000000000000000000000001010000000000000000000000000000010011000000000000000000000000000100100000000000000000000000000001000100000000000000000000000000010000000000000000000000000000000011110000000000000000000000000000111000000000000000000000000000001101000000000000000000000000000011000000000000000000000000000000101100000000000000000000000000001010000000000000000000000000000010010000000000000000000000000000100000000000000000000000000000000111000000000000000000000000000001100000000000000000000000000000010100000000000000000000000000000100000000000000000000000000000000110000000000000000000000000000001000000000000000000000000000000001 $
b10100 '
#210000
b10110 !
b10110 &
b10101 #
b10101 %
bx00000000000000000000000000010110000000000000000000000000000101010000000000000000000000000001010000000000000000000000000000010011000000000000000000000000000100100000000000000000000000000001000100000000000000000000000000010000000000000000000000000000000011110000000000000000000000000000111000000000000000000000000000001101000000000000000000000000000011000000000000000000000000000000101100000000000000000000000000001010000000000000000000000000000010010000000000000000000000000000100000000000000000000000000000000111000000000000000000000000000001100000000000000000000000000000010100000000000000000000000000000100000000000000000000000000000000110000000000000000000000000000001000000000000000000000000000000001 "
bx00000000000000000000000000010110000000000000000000000000000101010000000000000000000000000001010000000000000000000000000000010011000000000000000000000000000100100000000000000000000000000001000100000000000000000000000000010000000000000000000000000000000011110000000000000000000000000000111000000000000000000000000000001101000000000000000000000000000011000000000000000000000000000000101100000000000000000000000000001010000000000000000000000000000010010000000000000000000000000000100000000000000000000000000000000111000000000000000000000000000001100000000000000000000000000000010100000000000000000000000000000100000000000000000000000000000000110000000000000000000000000000001000000000000000000000000000000001 $
b10101 '
#220000
b10111 !
b10111 &
b10110 #
b10110 %
bx0000000000000000000000000001011100000000000000000000000000010110000000000000000000000000000101010000000000000000000000000001010000000000000000000000000000010011000000000000000000000000000100100000000000000000000000000001000100000000000000000000000000010000000000000000000000000000000011110000000000000000000000000000111000000000000000000000000000001101000000000000000000000000000011000000000000000000000000000000101100000000000000000000000000001010000000000000000000000000000010010000000000000000000000000000100000000000000000000000000000000111000000000000000000000000000001100000000000000000000000000000010100000000000000000000000000000100000000000000000000000000000000110000000000000000000000000000001000000000000000000000000000000001 "
bx0000000000000000000000000001011100000000000000000000000000010110000000000000000000000000000101010000000000000000000000000001010000000000000000000000000000010011000000000000000000000000000100100000000000000000000000000001000100000000000000000000000000010000000000000000000000000000000011110000000000000000000000000000111000000000000000000000000000001101000000000000000000000000000011000000000000000000000000000000101100000000000000000000000000001010000000000000000000000000000010010000000000000000000000000000100000000000000000000000000000000111000000000000000000000000000001100000000000000000000000000000010100000000000000000000000000000100000000000000000000000000000000110000000000000000000000000000001000000000000000000000000000000001 $
b10110 '
#230000
b11000 !
b11000 &
b10111 #
b10111 %
bx000000000000000000000000000110000000000000000000000000000001011100000000000000000000000000010110000000000000000000000000000101010000000000000000000000000001010000000000000000000000000000010011000000000000000000000000000100100000000000000000000000000001000100000000000000000000000000010000000000000000000000000000000011110000000000000000000000000000111000000000000000000000000000001101000000000000000000000000000011000000000000000000000000000000101100000000000000000000000000001010000000000000000000000000000010010000000000000000000000000000100000000000000000000000000000000111000000000000000000000000000001100000000000000000000000000000010100000000000000000000000000000100000000000000000000000000000000110000000000000000000000000000001000000000000000000000000000000001 "
bx000000000000000000000000000110000000000000000000000000000001011100000000000000000000000000010110000000000000000000000000000101010000000000000000000000000001010000000000000000000000000000010011000000000000000000000000000100100000000000000000000000000001000100000000000000000000000000010000000000000000000000000000000011110000000000000000000000000000111000000000000000000000000000001101000000000000000000000000000011000000000000000000000000000000101100000000000000000000000000001010000000000000000000000000000010010000000000000000000000000000100000000000000000000000000000000111000000000000000000000000000001100000000000000000000000000000010100000000000000000000000000000100000000000000000000000000000000110000000000000000000000000000001000000000000000000000000000000001 $
b10111 '
#240000
b11001 !
b11001 &
b11000 #
b11000 %
bx00000000000000000000000000011001000000000000000000000000000110000000000000000000000000000001011100000000000000000000000000010110000000000000000000000000000101010000000000000000000000000001010000000000000000000000000000010011000000000000000000000000000100100000000000000000000000000001000100000000000000000000000000010000000000000000000000000000000011110000000000000000000000000000111000000000000000000000000000001101000000000000000000000000000011000000000000000000000000000000101100000000000000000000000000001010000000000000000000000000000010010000000000000000000000000000100000000000000000000000000000000111000000000000000000000000000001100000000000000000000000000000010100000000000000000000000000000100000000000000000000000000000000110000000000000000000000000000001000000000000000000000000000000001 "
bx00000000000000000000000000011001000000000000000000000000000110000000000000000000000000000001011100000000000000000000000000010110000000000000000000000000000101010000000000000000000000000001010000000000000000000000000000010011000000000000000000000000000100100000000000000000000000000001000100000000000000000000000000010000000000000000000000000000000011110000000000000000000000000000111000000000000000000000000000001101000000000000000000000000000011000000000000000000000000000000101100000000000000000000000000001010000000000000000000000000000010010000000000000000000000000000100000000000000000000000000000000111000000000000000000000000000001100000000000000000000000000000010100000000000000000000000000000100000000000000000000000000000000110000000000000000000000000000001000000000000000000000000000000001 $
b11000 '
#250000
b11010 !
b11010 &
b11001 #
b11001 %
bx0000000000000000000000000001101000000000000000000000000000011001000000000000000000000000000110000000000000000000000000000001011100000000000000000000000000010110000000000000000000000000000101010000000000000000000000000001010000000000000000000000000000010011000000000000000000000000000100100000000000000000000000000001000100000000000000000000000000010000000000000000000000000000000011110000000000000000000000000000111000000000000000000000000000001101000000000000000000000000000011000000000000000000000000000000101100000000000000000000000000001010000000000000000000000000000010010000000000000000000000000000100000000000000000000000000000000111000000000000000000000000000001100000000000000000000000000000010100000000000000000000000000000100000000000000000000000000000000110000000000000000000000000000001000000000000000000000000000000001 "
bx0000000000000000000000000001101000000000000000000000000000011001000000000000000000000000000110000000000000000000000000000001011100000000000000000000000000010110000000000000000000000000000101010000000000000000000000000001010000000000000000000000000000010011000000000000000000000000000100100000000000000000000000000001000100000000000000000000000000010000000000000000000000000000000011110000000000000000000000000000111000000000000000000000000000001101000000000000000000000000000011000000000000000000000000000000101100000000000000000000000000001010000000000000000000000000000010010000000000000000000000000000100000000000000000000000000000000111000000000000000000000000000001100000000000000000000000000000010100000000000000000000000000000100000000000000000000000000000000110000000000000000000000000000001000000000000000000000000000000001 $
b11001 '
#260000
b11011 !
b11011 &
b11010 #
b11010 %
bx000000000000000000000000000110110000000000000000000000000001101000000000000000000000000000011001000000000000000000000000000110000000000000000000000000000001011100000000000000000000000000010110000000000000000000000000000101010000000000000000000000000001010000000000000000000000000000010011000000000000000000000000000100100000000000000000000000000001000100000000000000000000000000010000000000000000000000000000000011110000000000000000000000000000111000000000000000000000000000001101000000000000000000000000000011000000000000000000000000000000101100000000000000000000000000001010000000000000000000000000000010010000000000000000000000000000100000000000000000000000000000000111000000000000000000000000000001100000000000000000000000000000010100000000000000000000000000000100000000000000000000000000000000110000000000000000000000000000001000000000000000000000000000000001 "
bx000000000000000000000000000110110000000000000000000000000001101000000000000000000000000000011001000000000000000000000000000110000000000000000000000000000001011100000000000000000000000000010110000000000000000000000000000101010000000000000000000000000001010000000000000000000000000000010011000000000000000000000000000100100000000000000000000000000001000100000000000000000000000000010000000000000000000000000000000011110000000000000000000000000000111000000000000000000000000000001101000000000000000000000000000011000000000000000000000000000000101100000000000000000000000000001010000000000000000000000000000010010000000000000000000000000000100000000000000000000000000000000111000000000000000000000000000001100000000000000000000000000000010100000000000000000000000000000100000000000000000000000000000000110000000000000000000000000000001000000000000000000000000000000001 $
b11010 '
#270000
b11100 !
b11100 &
b11011 #
b11011 %
bx00000000000000000000000000011100000000000000000000000000000110110000000000000000000000000001101000000000000000000000000000011001000000000000000000000000000110000000000000000000000000000001011100000000000000000000000000010110000000000000000000000000000101010000000000000000000000000001010000000000000000000000000000010011000000000000000000000000000100100000000000000000000000000001000100000000000000000000000000010000000000000000000000000000000011110000000000000000000000000000111000000000000000000000000000001101000000000000000000000000000011000000000000000000000000000000101100000000000000000000000000001010000000000000000000000000000010010000000000000000000000000000100000000000000000000000000000000111000000000000000000000000000001100000000000000000000000000000010100000000000000000000000000000100000000000000000000000000000000110000000000000000000000000000001000000000000000000000000000000001 "
bx00000000000000000000000000011100000000000000000000000000000110110000000000000000000000000001101000000000000000000000000000011001000000000000000000000000000110000000000000000000000000000001011100000000000000000000000000010110000000000000000000000000000101010000000000000000000000000001010000000000000000000000000000010011000000000000000000000000000100100000000000000000000000000001000100000000000000000000000000010000000000000000000000000000000011110000000000000000000000000000111000000000000000000000000000001101000000000000000000000000000011000000000000000000000000000000101100000000000000000000000000001010000000000000000000000000000010010000000000000000000000000000100000000000000000000000000000000111000000000000000000000000000001100000000000000000000000000000010100000000000000000000000000000100000000000000000000000000000000110000000000000000000000000000001000000000000000000000000000000001 $
b11011 '
#280000
b11101 !
b11101 &
b11100 #
b11100 %
bx0000000000000000000000000001110100000000000000000000000000011100000000000000000000000000000110110000000000000000000000000001101000000000000000000000000000011001000000000000000000000000000110000000000000000000000000000001011100000000000000000000000000010110000000000000000000000000000101010000000000000000000000000001010000000000000000000000000000010011000000000000000000000000000100100000000000000000000000000001000100000000000000000000000000010000000000000000000000000000000011110000000000000000000000000000111000000000000000000000000000001101000000000000000000000000000011000000000000000000000000000000101100000000000000000000000000001010000000000000000000000000000010010000000000000000000000000000100000000000000000000000000000000111000000000000000000000000000001100000000000000000000000000000010100000000000000000000000000000100000000000000000000000000000000110000000000000000000000000000001000000000000000000000000000000001 "
bx0000000000000000000000000001110100000000000000000000000000011100000000000000000000000000000110110000000000000000000000000001101000000000000000000000000000011001000000000000000000000000000110000000000000000000000000000001011100000000000000000000000000010110000000000000000000000000000101010000000000000000000000000001010000000000000000000000000000010011000000000000000000000000000100100000000000000000000000000001000100000000000000000000000000010000000000000000000000000000000011110000000000000000000000000000111000000000000000000000000000001101000000000000000000000000000011000000000000000000000000000000101100000000000000000000000000001010000000000000000000000000000010010000000000000000000000000000100000000000000000000000000000000111000000000000000000000000000001100000000000000000000000000000010100000000000000000000000000000100000000000000000000000000000000110000000000000000000000000000001000000000000000000000000000000001 $
b11100 '
#290000
b11110 !
b11110 &
b11101 #
b11101 %
bx000000000000000000000000000111100000000000000000000000000001110100000000000000000000000000011100000000000000000000000000000110110000000000000000000000000001101000000000000000000000000000011001000000000000000000000000000110000000000000000000000000000001011100000000000000000000000000010110000000000000000000000000000101010000000000000000000000000001010000000000000000000000000000010011000000000000000000000000000100100000000000000000000000000001000100000000000000000000000000010000000000000000000000000000000011110000000000000000000000000000111000000000000000000000000000001101000000000000000000000000000011000000000000000000000000000000101100000000000000000000000000001010000000000000000000000000000010010000000000000000000000000000100000000000000000000000000000000111000000000000000000000000000001100000000000000000000000000000010100000000000000000000000000000100000000000000000000000000000000110000000000000000000000000000001000000000000000000000000000000001 "
bx000000000000000000000000000111100000000000000000000000000001110100000000000000000000000000011100000000000000000000000000000110110000000000000000000000000001101000000000000000000000000000011001000000000000000000000000000110000000000000000000000000000001011100000000000000000000000000010110000000000000000000000000000101010000000000000000000000000001010000000000000000000000000000010011000000000000000000000000000100100000000000000000000000000001000100000000000000000000000000010000000000000000000000000000000011110000000000000000000000000000111000000000000000000000000000001101000000000000000000000000000011000000000000000000000000000000101100000000000000000000000000001010000000000000000000000000000010010000000000000000000000000000100000000000000000000000000000000111000000000000000000000000000001100000000000000000000000000000010100000000000000000000000000000100000000000000000000000000000000110000000000000000000000000000001000000000000000000000000000000001 $
b11101 '
#300000
b11111 !
b11111 &
b11110 #
b11110 %
bx00000000000000000000000000011111000000000000000000000000000111100000000000000000000000000001110100000000000000000000000000011100000000000000000000000000000110110000000000000000000000000001101000000000000000000000000000011001000000000000000000000000000110000000000000000000000000000001011100000000000000000000000000010110000000000000000000000000000101010000000000000000000000000001010000000000000000000000000000010011000000000000000000000000000100100000000000000000000000000001000100000000000000000000000000010000000000000000000000000000000011110000000000000000000000000000111000000000000000000000000000001101000000000000000000000000000011000000000000000000000000000000101100000000000000000000000000001010000000000000000000000000000010010000000000000000000000000000100000000000000000000000000000000111000000000000000000000000000001100000000000000000000000000000010100000000000000000000000000000100000000000000000000000000000000110000000000000000000000000000001000000000000000000000000000000001 "
bx00000000000000000000000000011111000000000000000000000000000111100000000000000000000000000001110100000000000000000000000000011100000000000000000000000000000110110000000000000000000000000001101000000000000000000000000000011001000000000000000000000000000110000000000000000000000000000001011100000000000000000000000000010110000000000000000000000000000101010000000000000000000000000001010000000000000000000000000000010011000000000000000000000000000100100000000000000000000000000001000100000000000000000000000000010000000000000000000000000000000011110000000000000000000000000000111000000000000000000000000000001101000000000000000000000000000011000000000000000000000000000000101100000000000000000000000000001010000000000000000000000000000010010000000000000000000000000000100000000000000000000000000000000111000000000000000000000000000001100000000000000000000000000000010100000000000000000000000000000100000000000000000000000000000000110000000000000000000000000000001000000000000000000000000000000001 $
b11110 '
#310000
b100000 !
b100000 &
b11111 #
b11111 %
b10000000000000000000000000000000011111000000000000000000000000000111100000000000000000000000000001110100000000000000000000000000011100000000000000000000000000000110110000000000000000000000000001101000000000000000000000000000011001000000000000000000000000000110000000000000000000000000000001011100000000000000000000000000010110000000000000000000000000000101010000000000000000000000000001010000000000000000000000000000010011000000000000000000000000000100100000000000000000000000000001000100000000000000000000000000010000000000000000000000000000000011110000000000000000000000000000111000000000000000000000000000001101000000000000000000000000000011000000000000000000000000000000101100000000000000000000000000001010000000000000000000000000000010010000000000000000000000000000100000000000000000000000000000000111000000000000000000000000000001100000000000000000000000000000010100000000000000000000000000000100000000000000000000000000000000110000000000000000000000000000001000000000000000000000000000000001 "
b10000000000000000000000000000000011111000000000000000000000000000111100000000000000000000000000001110100000000000000000000000000011100000000000000000000000000000110110000000000000000000000000001101000000000000000000000000000011001000000000000000000000000000110000000000000000000000000000001011100000000000000000000000000010110000000000000000000000000000101010000000000000000000000000001010000000000000000000000000000010011000000000000000000000000000100100000000000000000000000000001000100000000000000000000000000010000000000000000000000000000000011110000000000000000000000000000111000000000000000000000000000001101000000000000000000000000000011000000000000000000000000000000101100000000000000000000000000001010000000000000000000000000000010010000000000000000000000000000100000000000000000000000000000000111000000000000000000000000000001100000000000000000000000000000010100000000000000000000000000000100000000000000000000000000000000110000000000000000000000000000001000000000000000000000000000000001 $
b11111 '
#320000
b100000 '
